Workbook

Sheet README
A1: Retail Inventory Control & Stock Reconciliation Workbook
A2: Nigerian FMCG distributor: beverages, noodles, cooking oil, home care and packaged food
A4: Purpose | B4: Tracks stock movements for one week, reconciles book stock to a physical count, raises reorder alerts, classifies fast and slow movers, and produces a weekly inventory report.
A5: SAMPLE DATA | B5: All product names, prices, suppliers, customers, quantities and investigation notes are fictitious illustrations for this exercise. Prices are not market quotes. Replace the blue cells with your own data.
A6: Reporting week | B6: Mon 19 Oct to Sat 24 Oct 2026 (6 trading days). Change the start date and trading days on the Settings sheet.
A7: Unit of stock | B7: Cartons / packs as stated in the Pack column on Products. Values are in Naira (₦) at cost unless stated.
A9: SHEET GUIDE
A10: Settings | B10: Week dates, safety days, alert buffers, variance tolerances, fast/slow thresholds. Edit blue cells only.
A11: Products | B11: Product master: code, supplier, pack, unit cost, selling price, supplier lead time.
A12: Transactions | B12: Daily log of purchases, sales (cash / transfer / credit), sales returns, supplier returns and damaged stock (203 sample lines).
A13: Register | B13: Inventory register. Expected closing = Opening + Stock Received + Sales Returns − Units Sold − Supplier Returns − Damaged. Enter opening stock and physical count here.
A14: Reconciliation | B14: STOCK RECONCILIATION REPORT: book vs physical, variance in units and ₦, priority flag and investigation notes.
A15: Reorder Dashboard | B15: REORDER ALERT DASHBOARD: minimum levels, alert status, suggested order quantities and values by supplier.
A16: Movers Analysis | B16: Fast / medium / slow classification using units sold and weekly stock turnover.
A17: Sales Summary | B17: Pivot-style SUMIFS tables: sales by day and payment type, and by category.
A18: Weekly Report | B18: WEEKLY INVENTORY PERFORMANCE SUMMARY: KPIs, losses, movers, auto-generated observations and charts.
A20: COLOUR CODE
A21: Blue text on yellow | B21: Input cell: you type or paste here.
A22: Black text | B22: Formula: do not overwrite.
A24: HOW TO ADD DATA
A25: 1. New transactions | B25: Add rows at the bottom of Transactions (up to row 1000). Enter date, product code, type, quantity, party and terms. Copy the formulas in columns D, E, J and K down from the row above.
A26: 2. Next week | B26: Update Settings start date, then set new Opening Stock (last week’s physical count) and clear the Physical Count column on Register.
A27: 3. Real PivotTable | B27: Select Transactions!A5:L(last row) > Insert > PivotTable. Suggested layout: Rows = Product Name, Columns = Txn Type, Values = Sum of Qty. This file uses SUMIFS tables instead because PivotTables cannot be generated programmatically here.
A29: KEY ASSUMPTIONS
A30: Valuation | B30: Purchases, supplier returns, damaged stock and variances are valued at unit cost. Sales and sales returns are valued at list selling price (no discounts modelled).
A31: Stock on hand | B31: Reorder Dashboard uses the physical count where entered, otherwise the book balance.
A32: Minimum stock | B32: Calculated as average daily sales × (supplier lead time + safety days). Type a figure in the Override column on Reorder Dashboard to set your own.
A33: Turnover | B33: Weekly turnover = units sold ÷ average of opening and closing stock. Annualised figure multiplies by 52 and is indicative only.
A34: Potential loss | B34: Stock shortages + damaged stock, both at cost. Overages are not netted off; supplier returns are excluded because they are recoverable by credit note.
A35: Classification | B35: Thresholds are set on Settings. They are practical starting points, not an industry standard. Tune them to your business.

Sheet Weekly Report
A1: =Settings!B4&" - Weekly Inventory Performance Summary" -> Eko Provisions Distribution Ltd (sample) - Weekly Inventory Performance Summary
A2: ="Week: "&TEXT(Settings!B5,"dd mmm yyyy")&" to "&TEXT(Settings!B7,"dd mmm yyyy")&" | Values in ₦ at cost unless stated | Sample data" -> Week: 19 Oct 2026 to 24 Oct 2026 | Values in ₦ at cost unless stated | Sample data
A4: 1. Sales and margin
A5: Gross sales (₦ at selling price) | B5: ='Sales Summary'!H12 -> 6588900
A6: Cash sales | B6: ='Sales Summary'!E12 -> 2077800 | C6: =IFERROR(B6/$B$5,0) -> 0.31534854
A7: Transfer sales | B7: ='Sales Summary'!F12 -> 1972900 | C7: =IFERROR(B7/$B$5,0) -> 0.29942783
A8: Credit sales (receivable) | B8: ='Sales Summary'!G12 -> 2538200 | C8: =IFERROR(B8/$B$5,0) -> 0.38522363
A9: Sales returns (₦ at selling price) | B9: ='Sales Summary'!I12 -> 139100
A10: Cost of goods sold (net of returns) | B10: =SUMPRODUCT(Register!G6:G23-Register!F6:F23,Register!M6:M23) -> 5804900
A11: Net sales | B11: =B5-B9 -> 6449800
A12: Gross margin (₦) | B12: =B11-B10 -> 644900
A13: Gross margin % | B13: =IFERROR(B12/B11,0) -> 0.099987597
A15: 2. Stock position
A16: Opening stock value | B16: =SUMPRODUCT(Register!D6:D23,Register!M6:M23) -> 10345900
A17: Purchases received | B17: =SUMPRODUCT(Register!E6:E23,Register!M6:M23) -> 3308300
A18: Closing stock value: book | B18: =SUMPRODUCT(Register!J6:J23,Register!M6:M23) -> 7672800
A19: Closing stock value: physical count | B19: =SUMPRODUCT(Register!K6:K23,Register!M6:M23) -> 7585900
A20: Stock availability (% of SKUs in stock) | B20: =COUNTIF('Reorder Dashboard'!E9:E26,">0")/COUNTA('Reorder Dashboard'!A9:A26) -> 0.94444444
A21: SKUs in stock-out | B21: ='Reorder Dashboard'!A5 -> 1
A22: SKUs at or below minimum (reorder now) | B22: ='Reorder Dashboard'!B5 -> 4
A23: SKUs approaching minimum | B23: ='Reorder Dashboard'!C5 -> 3
A24: Reorder requirement (₦ at cost) | B24: ='Reorder Dashboard'!E5 -> 3977800
A26: 3. Control: variances and potential losses
A27: SKUs with a stock variance | B27: =Reconciliation!B6+Reconciliation!B7 -> 7
A28: Stock record accuracy (% SKUs matching) | B28: =Reconciliation!B8 -> 0.61111111
A29: Shortage value | B29: =Reconciliation!E4 -> -112800
A30: Overage value | B30: =Reconciliation!E5 -> 25900
A31: Net variance | B31: =Reconciliation!E6 -> -86900
A32: Damaged stock | B32: =Reconciliation!E7 -> 123300
A33: Supplier returns (recoverable by credit note; not a loss) | B33: =SUMPRODUCT(Register!H6:H23,Register!M6:M23) -> 53200
A34: Total potential loss (shortages + damaged) | B34: =-B29+B32 -> 236100 | C34: =IFERROR(B34/B11,0) -> 0.036605786
A36: 4. Fast and slow movers
A37: Top 5 by units sold | B37: Units Sold | C37: Weekly Turnover | D37: Classification
A38: =INDEX('Movers Analysis'!$C$6:$C$23,MATCH(1,'Movers Analysis'!$A$6:$A$23,0)) -> Instant Noodles Chicken 70g | B38: =INDEX('Movers Analysis'!$D$6:$D$23,MATCH(1,'Movers Analysis'!$A$6:$A$23,0)) -> 90 | C38: =INDEX('Movers Analysis'!$H$6:$H$23,MATCH(1,'Movers Analysis'!$A$6:$A$23,0)) -> 0.80717489 | D38: =INDEX('Movers Analysis'!$K$6:$K$23,MATCH(1,'Movers Analysis'!$A$6:$A$23,0)) -> Medium
A39: =INDEX('Movers Analysis'!$C$6:$C$23,MATCH(2,'Movers Analysis'!$A$6:$A$23,0)) -> Table Water 75cl | B39: =INDEX('Movers Analysis'!$D$6:$D$23,MATCH(2,'Movers Analysis'!$A$6:$A$23,0)) -> 72 | C39: =INDEX('Movers Analysis'!$H$6:$H$23,MATCH(2,'Movers Analysis'!$A$6:$A$23,0)) -> 1.210084 | D39: =INDEX('Movers Analysis'!$K$6:$K$23,MATCH(2,'Movers Analysis'!$A$6:$A$23,0)) -> Fast-moving
A40: =INDEX('Movers Analysis'!$C$6:$C$23,MATCH(3,'Movers Analysis'!$A$6:$A$23,0)) -> Cola Soft Drink 50cl PET | B40: =INDEX('Movers Analysis'!$D$6:$D$23,MATCH(3,'Movers Analysis'!$A$6:$A$23,0)) -> 60 | C40: =INDEX('Movers Analysis'!$H$6:$H$23,MATCH(3,'Movers Analysis'!$A$6:$A$23,0)) -> 2.1428571 | D40: =INDEX('Movers Analysis'!$K$6:$K$23,MATCH(3,'Movers Analysis'!$A$6:$A$23,0)) -> Fast-moving
A41: =INDEX('Movers Analysis'!$C$6:$C$23,MATCH(4,'Movers Analysis'!$A$6:$A$23,0)) -> Instant Noodles Onion 70g | B41: =INDEX('Movers Analysis'!$D$6:$D$23,MATCH(4,'Movers Analysis'!$A$6:$A$23,0)) -> 54 | C41: =INDEX('Movers Analysis'!$H$6:$H$23,MATCH(4,'Movers Analysis'!$A$6:$A$23,0)) -> 4 | D41: =INDEX('Movers Analysis'!$K$6:$K$23,MATCH(4,'Movers Analysis'!$A$6:$A$23,0)) -> Fast-moving
A42: =INDEX('Movers Analysis'!$C$6:$C$23,MATCH(5,'Movers Analysis'!$A$6:$A$23,0)) -> Orange Soft Drink 50cl PET | B42: =INDEX('Movers Analysis'!$D$6:$D$23,MATCH(5,'Movers Analysis'!$A$6:$A$23,0)) -> 42 | C42: =INDEX('Movers Analysis'!$H$6:$H$23,MATCH(5,'Movers Analysis'!$A$6:$A$23,0)) -> 1.4736842 | D42: =INDEX('Movers Analysis'!$K$6:$K$23,MATCH(5,'Movers Analysis'!$A$6:$A$23,0)) -> Fast-moving
A44: Slowest 5 by turnover | B44: Units Sold | C44: Weekly Turnover | D44: Classification
A45: =INDEX('Movers Analysis'!$C$6:$C$23,MATCH(1,'Movers Analysis'!$L$6:$L$23,0)) -> Table Salt 500g | B45: =INDEX('Movers Analysis'!$D$6:$D$23,MATCH(1,'Movers Analysis'!$L$6:$L$23,0)) -> 4 | C45: =INDEX('Movers Analysis'!$H$6:$H$23,MATCH(1,'Movers Analysis'!$L$6:$L$23,0)) -> 0.18181818 | D45: =INDEX('Movers Analysis'!$K$6:$K$23,MATCH(1,'Movers Analysis'!$L$6:$L$23,0)) -> Slow-moving
A46: =INDEX('Movers Analysis'!$C$6:$C$23,MATCH(2,'Movers Analysis'!$L$6:$L$23,0)) -> Cocoa Beverage Powder 400g | B46: =INDEX('Movers Analysis'!$D$6:$D$23,MATCH(2,'Movers Analysis'!$L$6:$L$23,0)) -> 6 | C46: =INDEX('Movers Analysis'!$H$6:$H$23,MATCH(2,'Movers Analysis'!$L$6:$L$23,0)) -> 0.20689655 | D46: =INDEX('Movers Analysis'!$K$6:$K$23,MATCH(2,'Movers Analysis'!$L$6:$L$23,0)) -> Slow-moving
A47: =INDEX('Movers Analysis'!$C$6:$C$23,MATCH(3,'Movers Analysis'!$L$6:$L$23,0)) -> Laundry Bar Soap | B47: =INDEX('Movers Analysis'!$D$6:$D$23,MATCH(3,'Movers Analysis'!$L$6:$L$23,0)) -> 7 | C47: =INDEX('Movers Analysis'!$H$6:$H$23,MATCH(3,'Movers Analysis'!$L$6:$L$23,0)) -> 0.22222222 | D47: =INDEX('Movers Analysis'!$K$6:$K$23,MATCH(3,'Movers Analysis'!$L$6:$L$23,0)) -> Slow-moving
A48: =INDEX('Movers Analysis'!$C$6:$C$23,MATCH(4,'Movers Analysis'!$L$6:$L$23,0)) -> Malt Drink 33cl Can | B48: =INDEX('Movers Analysis'!$D$6:$D$23,MATCH(4,'Movers Analysis'!$L$6:$L$23,0)) -> 9 | C48: =INDEX('Movers Analysis'!$H$6:$H$23,MATCH(4,'Movers Analysis'!$L$6:$L$23,0)) -> 0.28125 | D48: =INDEX('Movers Analysis'!$K$6:$K$23,MATCH(4,'Movers Analysis'!$L$6:$L$23,0)) -> Slow-moving
A49: =INDEX('Movers Analysis'!$C$6:$C$23,MATCH(5,'Movers Analysis'!$L$6:$L$23,0)) -> Seasoning Cubes | B49: =INDEX('Movers Analysis'!$D$6:$D$23,MATCH(5,'Movers Analysis'!$L$6:$L$23,0)) -> 15 | C49: =INDEX('Movers Analysis'!$H$6:$H$23,MATCH(5,'Movers Analysis'!$L$6:$L$23,0)) -> 0.35294118 | D49: =INDEX('Movers Analysis'!$K$6:$K$23,MATCH(5,'Movers Analysis'!$L$6:$L$23,0)) -> Slow-moving
A51: 5. Key observations (formula-driven from the figures above)
A52: ="Net sales were ₦"&TEXT(B11,"#,##0")&" at a gross margin of "&TEXT(B13,"0.0%")&"; "&TEXT(C8,"0%")&" of gross sales were on credit and need collection follow-up." -> Net sales were ₦6,449,800 at a gross margin of 10.0%; 39% of gross sales were on credit and need collection follow-up.
A53: =(B21+B22)&" SKU(s) need reordering now ("&B21&" in stock-out) and "&B23&" more are approaching minimum. Estimated order value: ₦"&TEXT(B24,"#,##0")&"." -> 5 SKU(s) need reordering now (1 in stock-out) and 3 more are approaching minimum. Estimated order value: ₦3,977,800.
A54: ="The count found variances on "&B27&" SKU(s): shortages ₦"&TEXT(-B29,"#,##0")&", overages ₦"&TEXT(B30,"#,##0")&". "&Reconciliation!B9&" flagged HIGH priority for investigation." -> The count found variances on 7 SKU(s): shortages ₦112,800, overages ₦25,900. 5 flagged HIGH priority for investigation.
A55: ="Potential loss (shortages + damaged stock) is ₦"&TEXT(B34,"#,##0")&", or "&TEXT(C34,"0.0%")&" of net sales." -> Potential loss (shortages + damaged stock) is ₦236,100, or 3.7% of net sales.
A56: ="Best seller: "&A38&" ("&B38&" cartons). Slowest-turning: "&A45&" (turnover "&TEXT(C45,"0.00")&"x)." -> Best seller: Instant Noodles Chicken 70g (90 cartons). Slowest-turning: Table Salt 500g (turnover 0.18x).

Sheet Settings
A1: Settings and Assumptions
A2: Edit blue cells only. Every sheet reads these values.
A3: Parameter | B3: Value | C3: Note / source
A4: Business name | B4: Eko Provisions Distribution Ltd (sample) | C4: Fictitious business name for the exercise
A5: Week start date (Monday) | B5: 46314 | C5: Assumption: reporting week 19 to 24 Oct 2026
A6: Trading days in week | B6: 6 | C6: Assumption: Mon to Sat; Sunday closed
A7: Week end date | B7: =B5+B6-1 -> 46319 | C7: Formula: start + trading days − 1
A8: Safety stock (days of sales) | B8: 2 | C8: Assumption: buffer against late supplier deliveries
A9: Target stock cover when reordering (days) | B9: 14 | C9: Assumption: order up to 14 days of average sales
A10: "Approaching" alert buffer above minimum | B10: 0.25 | C10: Assumption: warn when stock is within 25% above minimum
A11: Variance tolerance (% of book balance) | B11: 0.05 | C11: Assumption: variances at or above 5% of book balance are flagged HIGH
A12: High-priority variance value (₦ at cost) | B12: 20000 | C12: Assumption: variances at or above ₦20,000 are flagged HIGH
A13: Fast-moving: weekly turnover at or above | B13: 1 | C13: Assumption: stock turns over at least once a week
A14: Slow-moving: weekly turnover below | B14: 0.5 | C14: Assumption: more than two weeks of stock on hand

Sheet Products
A1: Product Master
A2: Rows 6 to 60 are read by other sheets. Prices are illustrative (sample data).
A5: Product Code | B5: Product Name | C5: Category | D5: Supplier | E5: Pack Unit | F5: Unit Cost (₦) | G5: Selling Price (₦) | H5: Supplier Lead Time (days)
A6: BEV001 | B6: Cola Soft Drink 50cl PET | C6: Beverages | D6: Apapa Beverages Depot | E6: Carton of 12 | F6: 5200 | G6: 5900 | H6: 2
A7: BEV002 | B7: Orange Soft Drink 50cl PET | C7: Beverages | D7: Apapa Beverages Depot | E7: Carton of 12 | F7: 5200 | G7: 5900 | H7: 2
A8: BEV003 | B8: Table Water 75cl | C8: Beverages | D8: Apapa Beverages Depot | E8: Pack of 12 | F8: 1900 | G8: 2300 | H8: 2
A9: BEV004 | B9: Malt Drink 33cl Can | C9: Beverages | D9: Apapa Beverages Depot | E9: Carton of 24 | F9: 9800 | G9: 11200 | H9: 2
A10: NDL001 | B10: Instant Noodles Chicken 70g | C10: Noodles & Pasta | D10: Mushin Noodles & Foods Ltd | E10: Carton of 40 | F10: 7600 | G10: 8400 | H10: 3
A11: NDL002 | B11: Instant Noodles Onion 70g | C11: Noodles & Pasta | D11: Mushin Noodles & Foods Ltd | E11: Carton of 40 | F11: 7700 | G11: 8500 | H11: 3
A12: NDL003 | B12: Spaghetti 500g | C12: Noodles & Pasta | D12: Mushin Noodles & Foods Ltd | E12: Carton of 20 | F12: 11500 | G12: 12800 | H12: 3
A13: OIL001 | B13: Vegetable Oil 5L | C13: Cooking Oil | D13: Ikorodu Oil Mills (Agent) | E13: Carton of 4 | F13: 38000 | G13: 41500 | H13: 4
A14: OIL002 | B14: Vegetable Oil 1L | C14: Cooking Oil | D14: Ikorodu Oil Mills (Agent) | E14: Carton of 12 | F14: 36000 | G14: 39000 | H14: 4
A15: DET001 | B15: Detergent Powder 900g | C15: Home Care | D15: Oshodi Home Care Supplies | E15: Carton of 12 | F15: 14400 | G15: 16200 | H15: 3
A16: DET002 | B16: Detergent Powder 400g | C16: Home Care | D16: Oshodi Home Care Supplies | E16: Carton of 24 | F16: 17000 | G16: 19000 | H16: 3
A17: DET003 | B17: Laundry Bar Soap | C17: Home Care | D17: Oshodi Home Care Supplies | E17: Carton of 20 | F17: 9000 | G17: 10200 | H17: 3
... A23: FDS006 | B23: Cocoa Beverage Powder 400g | C23: Packaged Food | D23: Idumota Dry Goods Traders | E23: Carton of 12 | F23: 21000 | G23: 23500 | H23: 5

Sheet Transactions
A1: Daily Stock Movements
A2: Type must be: Purchase, Sale, Sales Return, Supplier Return or Damaged. Quantities are always positive; the Register applies the sign.
A3: Add new rows below the last line (to row 1000) and copy formulas in columns D, E, J, K down. Sale lines need Terms (Cash / Transfer / Credit).
A5: Date | B5: Txn Ref | C5: Product Code | D5: Product Name | E5: Category | F5: Txn Type | G5: Qty (cartons) | H5: Customer / Supplier | I5: Terms | J5: Unit Value (₦) | K5: Value (₦) | L5: Remarks
A6: 46314 | B6: TX-0001 | C6: BEV001 | D6: =IFERROR(INDEX(Products!$B$6:$B$60,MATCH(C6,Products!$A$6:$A$60,0)),"") -> Cola Soft Drink 50cl PET | E6: =IFERROR(INDEX(Products!$C$6:$C$60,MATCH(C6,Products!$A$6:$A$60,0)),"") -> Beverages | F6: Purchase | G6: 27 | H6: Apapa Beverages Depot | I6: Credit | J6: =IFERROR(IF(OR(F6="Sale",F6="Sales Return"),INDEX(Products!$G$6:$G$60,MATCH(C6,Products!$A$6:$A$60,0)),INDEX(Products!$F$6:$F$60,MATCH(C6,Products!$A$6:$A$60,0))),0) -> 5200 | K6: =G6*J6 -> 140400 | L6: Delivery note DN-2535
A7: 46314 | B7: TX-0002 | C7: BEV002 | D7: =IFERROR(INDEX(Products!$B$6:$B$60,MATCH(C7,Products!$A$6:$A$60,0)),"") -> Orange Soft Drink 50cl PET | E7: =IFERROR(INDEX(Products!$C$6:$C$60,MATCH(C7,Products!$A$6:$A$60,0)),"") -> Beverages | F7: Purchase | G7: 36 | H7: Apapa Beverages Depot | I7: Credit | J7: =IFERROR(IF(OR(F7="Sale",F7="Sales Return"),INDEX(Products!$G$6:$G$60,MATCH(C7,Products!$A$6:$A$60,0)),INDEX(Products!$F$6:$F$60,MATCH(C7,Products!$A$6:$A$60,0))),0) -> 5200 | K7: =G7*J7 -> 187200 | L7: Delivery note DN-2300
A8: 46314 | B8: TX-0003 | C8: BEV003 | D8: =IFERROR(INDEX(Products!$B$6:$B$60,MATCH(C8,Products!$A$6:$A$60,0)),"") -> Table Water 75cl | E8: =IFERROR(INDEX(Products!$C$6:$C$60,MATCH(C8,Products!$A$6:$A$60,0)),"") -> Beverages | F8: Purchase | G8: 33 | H8: Apapa Beverages Depot | I8: Cash | J8: =IFERROR(IF(OR(F8="Sale",F8="Sales Return"),INDEX(Products!$G$6:$G$60,MATCH(C8,Products!$A$6:$A$60,0)),INDEX(Products!$F$6:$F$60,MATCH(C8,Products!$A$6:$A$60,0))),0) -> 1900 | K8: =G8*J8 -> 62700 | L8: Delivery note DN-2426
A9: 46314 | B9: TX-0004 | C9: DET001 | D9: =IFERROR(INDEX(Products!$B$6:$B$60,MATCH(C9,Products!$A$6:$A$60,0)),"") -> Detergent Powder 900g | E9: =IFERROR(INDEX(Products!$C$6:$C$60,MATCH(C9,Products!$A$6:$A$60,0)),"") -> Home Care | F9: Purchase | G9: 24 | H9: Oshodi Home Care Supplies | I9: Credit | J9: =IFERROR(IF(OR(F9="Sale",F9="Sales Return"),INDEX(Products!$G$6:$G$60,MATCH(C9,Products!$A$6:$A$60,0)),INDEX(Products!$F$6:$F$60,MATCH(C9,Products!$A$6:$A$60,0))),0) -> 14400 | K9: =G9*J9 -> 345600 | L9: Delivery note DN-2256
A10: 46314 | B10: TX-0005 | C10: FDS001 | D10: =IFERROR(INDEX(Products!$B$6:$B$60,MATCH(C10,Products!$A$6:$A$60,0)),"") -> Evaporated Milk 160g Tin | E10: =IFERROR(INDEX(Products!$C$6:$C$60,MATCH(C10,Products!$A$6:$A$60,0)),"") -> Packaged Food | F10: Purchase | G10: 14 | H10: Idumota Dry Goods Traders | I10: Credit | J10: =IFERROR(IF(OR(F10="Sale",F10="Sales Return"),INDEX(Products!$G$6:$G$60,MATCH(C10,Products!$A$6:$A$60,0)),INDEX(Products!$F$6:$F$60,MATCH(C10,Products!$A$6:$A$60,0))),0) -> 28000 | K10: =G10*J10 -> 392000 | L10: Delivery note DN-2660
A11: 46314 | B11: TX-0006 | C11: FDS002 | D11: =IFERROR(INDEX(Products!$B$6:$B$60,MATCH(C11,Products!$A$6:$A$60,0)),"") -> Tomato Paste 70g Sachet | E11: =IFERROR(INDEX(Products!$C$6:$C$60,MATCH(C11,Products!$A$6:$A$60,0)),"") -> Packaged Food | F11: Purchase | G11: 20 | H11: Idumota Dry Goods Traders | I11: Credit | J11: =IFERROR(IF(OR(F11="Sale",F11="Sales Return"),INDEX(Products!$G$6:$G$60,MATCH(C11,Products!$A$6:$A$60,0)),INDEX(Products!$F$6:$F$60,MATCH(C11,Products!$A$6:$A$60,0))),0) -> 15500 | K11: =G11*J11 -> 310000 | L11: Delivery note DN-2104
A12: 46314 | B12: TX-0007 | C12: NDL001 | D12: =IFERROR(INDEX(Products!$B$6:$B$60,MATCH(C12,Products!$A$6:$A$60,0)),"") -> Instant Noodles Chicken 70g | E12: =IFERROR(INDEX(Products!$C$6:$C$60,MATCH(C12,Products!$A$6:$A$60,0)),"") -> Noodles & Pasta | F12: Purchase | G12: 40 | H12: Mushin Noodles & Foods Ltd | I12: Credit | J12: =IFERROR(IF(OR(F12="Sale",F12="Sales Return"),INDEX(Products!$G$6:$G$60,MATCH(C12,Products!$A$6:$A$60,0)),INDEX(Products!$F$6:$F$60,MATCH(C12,Products!$A$6:$A$60,0))),0) -> 7600 | K12: =G12*J12 -> 304000 | L12: Delivery note DN-2301
A13: 46314 | B13: TX-0008 | C13: NDL002 | D13: =IFERROR(INDEX(Products!$B$6:$B$60,MATCH(C13,Products!$A$6:$A$60,0)),"") -> Instant Noodles Onion 70g | E13: =IFERROR(INDEX(Products!$C$6:$C$60,MATCH(C13,Products!$A$6:$A$60,0)),"") -> Noodles & Pasta | F13: Purchase | G13: 29 | H13: Mushin Noodles & Foods Ltd | I13: Cash | J13: =IFERROR(IF(OR(F13="Sale",F13="Sales Return"),INDEX(Products!$G$6:$G$60,MATCH(C13,Products!$A$6:$A$60,0)),INDEX(Products!$F$6:$F$60,MATCH(C13,Products!$A$6:$A$60,0))),0) -> 7700 | K13: =G13*J13 -> 223300 | L13: Delivery note DN-2600
A14: 46314 | B14: TX-0009 | C14: OIL001 | D14: =IFERROR(INDEX(Products!$B$6:$B$60,MATCH(C14,Products!$A$6:$A$60,0)),"") -> Vegetable Oil 5L | E14: =IFERROR(INDEX(Products!$C$6:$C$60,MATCH(C14,Products!$A$6:$A$60,0)),"") -> Cooking Oil | F14: Purchase | G14: 22 | H14: Ikorodu Oil Mills (Agent) | I14: Cash | J14: =IFERROR(IF(OR(F14="Sale",F14="Sales Return"),INDEX(Products!$G$6:$G$60,MATCH(C14,Products!$A$6:$A$60,0)),INDEX(Products!$F$6:$F$60,MATCH(C14,Products!$A$6:$A$60,0))),0) -> 38000 | K14: =G14*J14 -> 836000 | L14: Delivery note DN-2258
A15: 46314 | B15: TX-0010 | C15: BEV001 | D15: =IFERROR(INDEX(Products!$B$6:$B$60,MATCH(C15,Products!$A$6:$A$60,0)),"") -> Cola Soft Drink 50cl PET | E15: =IFERROR(INDEX(Products!$C$6:$C$60,MATCH(C15,Products!$A$6:$A$60,0)),"") -> Beverages | F15: Sale | G15: 2 | H15: Sunrise Supermarket, Yaba | I15: Credit | J15: =IFERROR(IF(OR(F15="Sale",F15="Sales Return"),INDEX(Products!$G$6:$G$60,MATCH(C15,Products!$A$6:$A$60,0)),INDEX(Products!$F$6:$F$60,MATCH(C15,Products!$A$6:$A$60,0))),0) -> 5900 | K15: =G15*J15 -> 11800
A16: 46314 | B16: TX-0011 | C16: BEV001 | D16: =IFERROR(INDEX(Products!$B$6:$B$60,MATCH(C16,Products!$A$6:$A$60,0)),"") -> Cola Soft Drink 50cl PET | E16: =IFERROR(INDEX(Products!$C$6:$C$60,MATCH(C16,Products!$A$6:$A$60,0)),"") -> Beverages | F16: Sale | G16: 4 | H16: Madam Ngozi Shop, Oshodi | I16: Credit | J16: =IFERROR(IF(OR(F16="Sale",F16="Sales Return"),INDEX(Products!$G$6:$G$60,MATCH(C16,Products!$A$6:$A$60,0)),INDEX(Products!$F$6:$F$60,MATCH(C16,Products!$A$6:$A$60,0))),0) -> 5900 | K16: =G16*J16 -> 23600
A17: 46314 | B17: TX-0012 | C17: BEV001 | D17: =IFERROR(INDEX(Products!$B$6:$B$60,MATCH(C17,Products!$A$6:$A$60,0)),"") -> Cola Soft Drink 50cl PET | E17: =IFERROR(INDEX(Products!$C$6:$C$60,MATCH(C17,Products!$A$6:$A$60,0)),"") -> Beverages | F17: Sale | G17: 3 | H17: Alhaji Bello Stores, Idumota | I17: Transfer | J17: =IFERROR(IF(OR(F17="Sale",F17="Sales Return"),INDEX(Products!$G$6:$G$60,MATCH(C17,Products!$A$6:$A$60,0)),INDEX(Products!$F$6:$F$60,MATCH(C17,Products!$A$6:$A$60,0))),0) -> 5900 | K17: =G17*J17 -> 17700
A18: 46314 | B18: TX-0013 | C18: BEV002 | D18: =IFERROR(INDEX(Products!$B$6:$B$60,MATCH(C18,Products!$A$6:$A$60,0)),"") -> Orange Soft Drink 50cl PET | E18: =IFERROR(INDEX(Products!$C$6:$C$60,MATCH(C18,Products!$A$6:$A$60,0)),"") -> Beverages | F18: Sale | G18: 6 | H18: Sunrise Supermarket, Yaba | I18: Transfer | J18: =IFERROR(IF(OR(F18="Sale",F18="Sales Return"),INDEX(Products!$G$6:$G$60,MATCH(C18,Products!$A$6:$A$60,0)),INDEX(Products!$F$6:$F$60,MATCH(C18,Products!$A$6:$A$60,0))),0) -> 5900 | K18: =G18*J18 -> 35400
A19: 46314 | B19: TX-0014 | C19: BEV003 | D19: =IFERROR(INDEX(Products!$B$6:$B$60,MATCH(C19,Products!$A$6:$A$60,0)),"") -> Table Water 75cl | E19: =IFERROR(INDEX(Products!$C$6:$C$60,MATCH(C19,Products!$A$6:$A$60,0)),"") -> Beverages | F19: Sale | G19: 12 | H19: Sunrise Supermarket, Yaba | I19: Transfer | J19: =IFERROR(IF(OR(F19="Sale",F19="Sales Return"),INDEX(Products!$G$6:$G$60,MATCH(C19,Products!$A$6:$A$60,0)),INDEX(Products!$F$6:$F$60,MATCH(C19,Products!$A$6:$A$60,0))),0) -> 2300 | K19: =G19*J19 -> 27600
A20: 46314 | B20: TX-0015 | C20: BEV004 | D20: =IFERROR(INDEX(Products!$B$6:$B$60,MATCH(C20,Products!$A$6:$A$60,0)),"") -> Malt Drink 33cl Can | E20: =IFERROR(INDEX(Products!$C$6:$C$60,MATCH(C20,Products!$A$6:$A$60,0)),"") -> Beverages | F20: Sale | G20: 1 | H20: Sunrise Supermarket, Yaba | I20: Credit | J20: =IFERROR(IF(OR(F20="Sale",F20="Sales Return"),INDEX(Products!$G$6:$G$60,MATCH(C20,Products!$A$6:$A$60,0)),INDEX(Products!$F$6:$F$60,MATCH(C20,Products!$A$6:$A$60,0))),0) -> 11200 | K20: =G20*J20 -> 11200
A21: 46314 | B21: TX-0016 | C21: BEV004 | D21: =IFERROR(INDEX(Products!$B$6:$B$60,MATCH(C21,Products!$A$6:$A$60,0)),"") -> Malt Drink 33cl Can | E21: =IFERROR(INDEX(Products!$C$6:$C$60,MATCH(C21,Products!$A$6:$A$60,0)),"") -> Beverages | F21: Sale | G21: 1 | H21: Ebenezer Provision Store, Ajegunle | I21: Cash | J21: =IFERROR(IF(OR(F21="Sale",F21="Sales Return"),INDEX(Products!$G$6:$G$60,MATCH(C21,Products!$A$6:$A$60,0)),INDEX(Products!$F$6:$F$60,MATCH(C21,Products!$A$6:$A$60,0))),0) -> 11200 | K21: =G21*J21 -> 11200
A22: 46314 | B22: TX-0017 | C22: BEV004 | D22: =IFERROR(INDEX(Products!$B$6:$B$60,MATCH(C22,Products!$A$6:$A$60,0)),"") -> Malt Drink 33cl Can | E22: =IFERROR(INDEX(Products!$C$6:$C$60,MATCH(C22,Products!$A$6:$A$60,0)),"") -> Beverages | F22: Sale | G22: 1 | H22: Sunrise Supermarket, Yaba | I22: Credit | J22: =IFERROR(IF(OR(F22="Sale",F22="Sales Return"),INDEX(Products!$G$6:$G$60,MATCH(C22,Products!$A$6:$A$60,0)),INDEX(Products!$F$6:$F$60,MATCH(C22,Products!$A$6:$A$60,0))),0) -> 11200 | K22: =G22*J22 -> 11200
A23: 46314 | B23: TX-0018 | C23: DET001 | D23: =IFERROR(INDEX(Products!$B$6:$B$60,MATCH(C23,Products!$A$6:$A$60,0)),"") -> Detergent Powder 900g | E23: =IFERROR(INDEX(Products!$C$6:$C$60,MATCH(C23,Products!$A$6:$A$60,0)),"") -> Home Care | F23: Sale | G23: 2 | H23: Alhaji Bello Stores, Idumota | I23: Credit | J23: =IFERROR(IF(OR(F23="Sale",F23="Sales Return"),INDEX(Products!$G$6:$G$60,MATCH(C23,Products!$A$6:$A$60,0)),INDEX(Products!$F$6:$F$60,MATCH(C23,Products!$A$6:$A$60,0))),0) -> 16200 | K23: =G23*J23 -> 32400
A24: 46314 | B24: TX-0019 | C24: DET001 | D24: =IFERROR(INDEX(Products!$B$6:$B$60,MATCH(C24,Products!$A$6:$A$60,0)),"") -> Detergent Powder 900g | E24: =IFERROR(INDEX(Products!$C$6:$C$60,MATCH(C24,Products!$A$6:$A$60,0)),"") -> Home Care | F24: Sale | G24: 3 | H24: Oluwaseun Mini-Mart, Surulere | I24: Transfer | J24: =IFERROR(IF(OR(F24="Sale",F24="Sales Return"),INDEX(Products!$G$6:$G$60,MATCH(C24,Products!$A$6:$A$60,0)),INDEX(Products!$F$6:$F$60,MATCH(C24,Products!$A$6:$A$60,0))),0) -> 16200 | K24: =G24*J24 -> 48600
A25: 46314 | B25: TX-0020 | C25: DET002 | D25: =IFERROR(INDEX(Products!$B$6:$B$60,MATCH(C25,Products!$A$6:$A$60,0)),"") -> Detergent Powder 400g | E25: =IFERROR(INDEX(Products!$C$6:$C$60,MATCH(C25,Products!$A$6:$A$60,0)),"") -> Home Care | F25: Sale | G25: 2 | H25: Mama Chidi Provisions, Mushin | I25: Cash | J25: =IFERROR(IF(OR(F25="Sale",F25="Sales Return"),INDEX(Products!$G$6:$G$60,MATCH(C25,Products!$A$6:$A$60,0)),INDEX(Products!$F$6:$F$60,MATCH(C25,Products!$A$6:$A$60,0))),0) -> 19000 | K25: =G25*J25 -> 38000
A26: 46314 | B26: TX-0021 | C26: DET002 | D26: =IFERROR(INDEX(Products!$B$6:$B$60,MATCH(C26,Products!$A$6:$A$60,0)),"") -> Detergent Powder 400g | E26: =IFERROR(INDEX(Products!$C$6:$C$60,MATCH(C26,Products!$A$6:$A$60,0)),"") -> Home Care | F26: Sale | G26: 1 | H26: Greenfield Supermarket, Ikeja | I26: Credit | J26: =IFERROR(IF(OR(F26="Sale",F26="Sales Return"),INDEX(Products!$G$6:$G$60,MATCH(C26,Products!$A$6:$A$60,0)),INDEX(Products!$F$6:$F$60,MATCH(C26,Products!$A$6:$A$60,0))),0) -> 19000 | K26: =G26*J26 -> 19000
... A47: 46314 | B47: TX-0042 | C47: OIL002 | D47: =IFERROR(INDEX(Products!$B$6:$B$60,MATCH(C47,Products!$A$6:$A$60,0)),"") -> Vegetable Oil 1L | E47: =IFERROR(INDEX(Products!$C$6:$C$60,MATCH(C47,Products!$A$6:$A$60,0)),"") -> Cooking Oil | F47: Sale | G47: 1 | H47: Mama Chidi Provisions, Mushin | I47: Cash | J47: =IFERROR(IF(OR(F47="Sale",F47="Sales Return"),INDEX(Products!$G$6:$G$60,MATCH(C47,Products!$A$6:$A$60,0)),INDEX(Products!$F$6:$F$60,MATCH(C47,Products!$A$6:$A$60,0))),0) -> 39000 | K47: =G47*J47 -> 39000
A48: 46314 | B48: TX-0043 | C48: BEV002 | D48: =IFERROR(INDEX(Products!$B$6:$B$60,MATCH(C48,Products!$A$6:$A$60,0)),"") -> Orange Soft Drink 50cl PET | E48: =IFERROR(INDEX(Products!$C$6:$C$60,MATCH(C48,Products!$A$6:$A$60,0)),"") -> Beverages | F48: Damaged | G48: 1 | H48: Warehouse | J48: =IFERROR(IF(OR(F48="Sale",F48="Sales Return"),INDEX(Products!$G$6:$G$60,MATCH(C48,Products!$A$6:$A$60,0)),INDEX(Products!$F$6:$F$60,MATCH(C48,Products!$A$6:$A$60,0))),0) -> 5200 | K48: =G48*J48 -> 5200 | L48: Broken bottles during offloading
A49: 46315 | B49: TX-0044 | C49: DET001 | D49: =IFERROR(INDEX(Products!$B$6:$B$60,MATCH(C49,Products!$A$6:$A$60,0)),"") -> Detergent Powder 900g | E49: =IFERROR(INDEX(Products!$C$6:$C$60,MATCH(C49,Products!$A$6:$A$60,0)),"") -> Home Care | F49: Sales Return | G49: 1 | H49: Madam Ngozi Shop, Oshodi | J49: =IFERROR(IF(OR(F49="Sale",F49="Sales Return"),INDEX(Products!$G$6:$G$60,MATCH(C49,Products!$A$6:$A$60,0)),INDEX(Products!$F$6:$F$60,MATCH(C49,Products!$A$6:$A$60,0))),0) -> 16200 | K49: =G49*J49 -> 16200 | L49: Wrong variant delivered
A50: 46315 | B50: TX-0045 | C50: BEV001 | D50: =IFERROR(INDEX(Products!$B$6:$B$60,MATCH(C50,Products!$A$6:$A$60,0)),"") -> Cola Soft Drink 50cl PET | E50: =IFERROR(INDEX(Products!$C$6:$C$60,MATCH(C50,Products!$A$6:$A$60,0)),"") -> Beverages | F50: Sale | G50: 4 | H50: Balogun Market Stall 14, Lagos Island | I50: Cash | J50: =IFERROR(IF(OR(F50="Sale",F50="Sales Return"),INDEX(Products!$G$6:$G$60,MATCH(C50,Products!$A$6:$A$60,0)),INDEX(Products!$F$6:$F$60,MATCH(C50,Products!$A$6:$A$60,0))),0) -> 5900 | K50: =G50*J50 -> 23600
A51: 46315 | B51: TX-0046 | C51: BEV001 | D51: =IFERROR(INDEX(Products!$B$6:$B$60,MATCH(C51,Products!$A$6:$A$60,0)),"") -> Cola Soft Drink 50cl PET | E51: =IFERROR(INDEX(Products!$C$6:$C$60,MATCH(C51,Products!$A$6:$A$60,0)),"") -> Beverages | F51: Sale | G51: 2 | H51: Balogun Market Stall 14, Lagos Island | I51: Cash | J51: =IFERROR(IF(OR(F51="Sale",F51="Sales Return"),INDEX(Products!$G$6:$G$60,MATCH(C51,Products!$A$6:$A$60,0)),INDEX(Products!$F$6:$F$60,MATCH(C51,Products!$A$6:$A$60,0))),0) -> 5900 | K51: =G51*J51 -> 11800
A52: 46315 | B52: TX-0047 | C52: BEV002 | D52: =IFERROR(INDEX(Products!$B$6:$B$60,MATCH(C52,Products!$A$6:$A$60,0)),"") -> Orange Soft Drink 50cl PET | E52: =IFERROR(INDEX(Products!$C$6:$C$60,MATCH(C52,Products!$A$6:$A$60,0)),"") -> Beverages | F52: Sale | G52: 6 | H52: Ebenezer Provision Store, Ajegunle | I52: Credit | J52: =IFERROR(IF(OR(F52="Sale",F52="Sales Return"),INDEX(Products!$G$6:$G$60,MATCH(C52,Products!$A$6:$A$60,0)),INDEX(Products!$F$6:$F$60,MATCH(C52,Products!$A$6:$A$60,0))),0) -> 5900 | K52: =G52*J52 -> 35400
A53: 46315 | B53: TX-0048 | C53: BEV003 | D53: =IFERROR(INDEX(Products!$B$6:$B$60,MATCH(C53,Products!$A$6:$A$60,0)),"") -> Table Water 75cl | E53: =IFERROR(INDEX(Products!$C$6:$C$60,MATCH(C53,Products!$A$6:$A$60,0)),"") -> Beverages | F53: Sale | G53: 7 | H53: Mama Chidi Provisions, Mushin | I53: Cash | J53: =IFERROR(IF(OR(F53="Sale",F53="Sales Return"),INDEX(Products!$G$6:$G$60,MATCH(C53,Products!$A$6:$A$60,0)),INDEX(Products!$F$6:$F$60,MATCH(C53,Products!$A$6:$A$60,0))),0) -> 2300 | K53: =G53*J53 -> 16100
A54: 46315 | B54: TX-0049 | C54: BEV003 | D54: =IFERROR(INDEX(Products!$B$6:$B$60,MATCH(C54,Products!$A$6:$A$60,0)),"") -> Table Water 75cl | E54: =IFERROR(INDEX(Products!$C$6:$C$60,MATCH(C54,Products!$A$6:$A$60,0)),"") -> Beverages | F54: Sale | G54: 7 | H54: Oluwaseun Mini-Mart, Surulere | I54: Cash | J54: =IFERROR(IF(OR(F54="Sale",F54="Sales Return"),INDEX(Products!$G$6:$G$60,MATCH(C54,Products!$A$6:$A$60,0)),INDEX(Products!$F$6:$F$60,MATCH(C54,Products!$A$6:$A$60,0))),0) -> 2300 | K54: =G54*J54 -> 16100
A55: 46315 | B55: TX-0050 | C55: BEV004 | D55: =IFERROR(INDEX(Products!$B$6:$B$60,MATCH(C55,Products!$A$6:$A$60,0)),"") -> Malt Drink 33cl Can | E55: =IFERROR(INDEX(Products!$C$6:$C$60,MATCH(C55,Products!$A$6:$A$60,0)),"") -> Beverages | F55: Sale | G55: 2 | H55: Sunrise Supermarket, Yaba | I55: Credit | J55: =IFERROR(IF(OR(F55="Sale",F55="Sales Return"),INDEX(Products!$G$6:$G$60,MATCH(C55,Products!$A$6:$A$60,0)),INDEX(Products!$F$6:$F$60,MATCH(C55,Products!$A$6:$A$60,0))),0) -> 11200 | K55: =G55*J55 -> 22400
A56: 46315 | B56: TX-0051 | C56: DET001 | D56: =IFERROR(INDEX(Products!$B$6:$B$60,MATCH(C56,Products!$A$6:$A$60,0)),"") -> Detergent Powder 900g | E56: =IFERROR(INDEX(Products!$C$6:$C$60,MATCH(C56,Products!$A$6:$A$60,0)),"") -> Home Care | F56: Sale | G56: 2 | H56: Mama Chidi Provisions, Mushin | I56: Credit | J56: =IFERROR(IF(OR(F56="Sale",F56="Sales Return"),INDEX(Products!$G$6:$G$60,MATCH(C56,Products!$A$6:$A$60,0)),INDEX(Products!$F$6:$F$60,MATCH(C56,Products!$A$6:$A$60,0))),0) -> 16200 | K56: =G56*J56 -> 32400
A57: 46315 | B57: TX-0052 | C57: DET001 | D57: =IFERROR(INDEX(Products!$B$6:$B$60,MATCH(C57,Products!$A$6:$A$60,0)),"") -> Detergent Powder 900g | E57: =IFERROR(INDEX(Products!$C$6:$C$60,MATCH(C57,Products!$A$6:$A$60,0)),"") -> Home Care | F57: Sale | G57: 1 | H57: Ebenezer Provision Store, Ajegunle | I57: Credit | J57: =IFERROR(IF(OR(F57="Sale",F57="Sales Return"),INDEX(Products!$G$6:$G$60,MATCH(C57,Products!$A$6:$A$60,0)),INDEX(Products!$F$6:$F$60,MATCH(C57,Products!$A$6:$A$60,0))),0) -> 16200 | K57: =G57*J57 -> 16200
A58: 46315 | B58: TX-0053 | C58: DET002 | D58: =IFERROR(INDEX(Products!$B$6:$B$60,MATCH(C58,Products!$A$6:$A$60,0)),"") -> Detergent Powder 400g | E58: =IFERROR(INDEX(Products!$C$6:$C$60,MATCH(C58,Products!$A$6:$A$60,0)),"") -> Home Care | F58: Sale | G58: 1 | H58: Sunrise Supermarket, Yaba | I58: Credit | J58: =IFERROR(IF(OR(F58="Sale",F58="Sales Return"),INDEX(Products!$G$6:$G$60,MATCH(C58,Products!$A$6:$A$60,0)),INDEX(Products!$F$6:$F$60,MATCH(C58,Products!$A$6:$A$60,0))),0) -> 19000 | K58: =G58*J58 -> 19000
A59: 46315 | B59: TX-0054 | C59: FDS001 | D59: =IFERROR(INDEX(Products!$B$6:$B$60,MATCH(C59,Products!$A$6:$A$60,0)),"") -> Evaporated Milk 160g Tin | E59: =IFERROR(INDEX(Products!$C$6:$C$60,MATCH(C59,Products!$A$6:$A$60,0)),"") -> Packaged Food | F59: Sale | G59: 2 | H59: Madam Ngozi Shop, Oshodi | I59: Cash | J59: =IFERROR(IF(OR(F59="Sale",F59="Sales Return"),INDEX(Products!$G$6:$G$60,MATCH(C59,Products!$A$6:$A$60,0)),INDEX(Products!$F$6:$F$60,MATCH(C59,Products!$A$6:$A$60,0))),0) -> 31000 | K59: =G59*J59 -> 62000
A60: 46315 | B60: TX-0055 | C60: FDS002 | D60: =IFERROR(INDEX(Products!$B$6:$B$60,MATCH(C60,Products!$A$6:$A$60,0)),"") -> Tomato Paste 70g Sachet | E60: =IFERROR(INDEX(Products!$C$6:$C$60,MATCH(C60,Products!$A$6:$A$60,0)),"") -> Packaged Food | F60: Sale | G60: 1 | H60: Madam Ngozi Shop, Oshodi | I60: Transfer | J60: =IFERROR(IF(OR(F60="Sale",F60="Sales Return"),INDEX(Products!$G$6:$G$60,MATCH(C60,Products!$A$6:$A$60,0)),INDEX(Products!$F$6:$F$60,MATCH(C60,Products!$A$6:$A$60,0))),0) -> 17200 | K60: =G60*J60 -> 17200
A61: 46315 | B61: TX-0056 | C61: FDS002 | D61: =IFERROR(INDEX(Products!$B$6:$B$60,MATCH(C61,Products!$A$6:$A$60,0)),"") -> Tomato Paste 70g Sachet | E61: =IFERROR(INDEX(Products!$C$6:$C$60,MATCH(C61,Products!$A$6:$A$60,0)),"") -> Packaged Food | F61: Sale | G61: 4 | H61: Ebenezer Provision Store, Ajegunle | I61: Cash | J61: =IFERROR(IF(OR(F61="Sale",F61="Sales Return"),INDEX(Products!$G$6:$G$60,MATCH(C61,Products!$A$6:$A$60,0)),INDEX(Products!$F$6:$F$60,MATCH(C61,Products!$A$6:$A$60,0))),0) -> 17200 | K61: =G61*J61 -> 68800
... A76: 46315 | B76: TX-0071 | C76: OIL002 | D76: =IFERROR(INDEX(Products!$B$6:$B$60,MATCH(C76,Products!$A$6:$A$60,0)),"") -> Vegetable Oil 1L | E76: =IFERROR(INDEX(Products!$C$6:$C$60,MATCH(C76,Products!$A$6:$A$60,0)),"") -> Cooking Oil | F76: Sale | G76: 1 | H76: Oluwaseun Mini-Mart, Surulere | I76: Transfer | J76: =IFERROR(IF(OR(F76="Sale",F76="Sales Return"),INDEX(Products!$G$6:$G$60,MATCH(C76,Products!$A$6:$A$60,0)),INDEX(Products!$F$6:$F$60,MATCH(C76,Products!$A$6:$A$60,0))),0) -> 39000 | K76: =G76*J76 -> 39000
A77: 46315 | B77: TX-0072 | C77: BEV004 | D77: =IFERROR(INDEX(Products!$B$6:$B$60,MATCH(C77,Products!$A$6:$A$60,0)),"") -> Malt Drink 33cl Can | E77: =IFERROR(INDEX(Products!$C$6:$C$60,MATCH(C77,Products!$A$6:$A$60,0)),"") -> Beverages | F77: Supplier Return | G77: 1 | H77: Apapa Beverages Depot | J77: =IFERROR(IF(OR(F77="Sale",F77="Sales Return"),INDEX(Products!$G$6:$G$60,MATCH(C77,Products!$A$6:$A$60,0)),INDEX(Products!$F$6:$F$60,MATCH(C77,Products!$A$6:$A$60,0))),0) -> 9800 | K77: =G77*J77 -> 9800 | L77: Wrong brand supplied
A78: 46315 | B78: TX-0073 | C78: DET002 | D78: =IFERROR(INDEX(Products!$B$6:$B$60,MATCH(C78,Products!$A$6:$A$60,0)),"") -> Detergent Powder 400g | E78: =IFERROR(INDEX(Products!$C$6:$C$60,MATCH(C78,Products!$A$6:$A$60,0)),"") -> Home Care | F78: Damaged | G78: 1 | H78: Warehouse | J78: =IFERROR(IF(OR(F78="Sale",F78="Sales Return"),INDEX(Products!$G$6:$G$60,MATCH(C78,Products!$A$6:$A$60,0)),INDEX(Products!$F$6:$F$60,MATCH(C78,Products!$A$6:$A$60,0))),0) -> 17000 | K78: =G78*J78 -> 17000 | L78: Torn packs
A79: 46316 | B79: TX-0074 | C79: BEV001 | D79: =IFERROR(INDEX(Products!$B$6:$B$60,MATCH(C79,Products!$A$6:$A$60,0)),"") -> Cola Soft Drink 50cl PET | E79: =IFERROR(INDEX(Products!$C$6:$C$60,MATCH(C79,Products!$A$6:$A$60,0)),"") -> Beverages | F79: Purchase | G79: 27 | H79: Apapa Beverages Depot | I79: Cash | J79: =IFERROR(IF(OR(F79="Sale",F79="Sales Return"),INDEX(Products!$G$6:$G$60,MATCH(C79,Products!$A$6:$A$60,0)),INDEX(Products!$F$6:$F$60,MATCH(C79,Products!$A$6:$A$60,0))),0) -> 5200 | K79: =G79*J79 -> 140400 | L79: Delivery note DN-2165
A80: 46316 | B80: TX-0075 | C80: BEV003 | D80: =IFERROR(INDEX(Products!$B$6:$B$60,MATCH(C80,Products!$A$6:$A$60,0)),"") -> Table Water 75cl | E80: =IFERROR(INDEX(Products!$C$6:$C$60,MATCH(C80,Products!$A$6:$A$60,0)),"") -> Beverages | F80: Purchase | G80: 33 | H80: Apapa Beverages Depot | I80: Credit | J80: =IFERROR(IF(OR(F80="Sale",F80="Sales Return"),INDEX(Products!$G$6:$G$60,MATCH(C80,Products!$A$6:$A$60,0)),INDEX(Products!$F$6:$F$60,MATCH(C80,Products!$A$6:$A$60,0))),0) -> 1900 | K80: =G80*J80 -> 62700 | L80: Delivery note DN-2655
A81: 46316 | B81: TX-0076 | C81: NDL001 | D81: =IFERROR(INDEX(Products!$B$6:$B$60,MATCH(C81,Products!$A$6:$A$60,0)),"") -> Instant Noodles Chicken 70g | E81: =IFERROR(INDEX(Products!$C$6:$C$60,MATCH(C81,Products!$A$6:$A$60,0)),"") -> Noodles & Pasta | F81: Purchase | G81: 40 | H81: Mushin Noodles & Foods Ltd | I81: Cash | J81: =IFERROR(IF(OR(F81="Sale",F81="Sales Return"),INDEX(Products!$G$6:$G$60,MATCH(C81,Products!$A$6:$A$60,0)),INDEX(Products!$F$6:$F$60,MATCH(C81,Products!$A$6:$A$60,0))),0) -> 7600 | K81: =G81*J81 -> 304000 | L81: Delivery note DN-2325
A82: 46316 | B82: TX-0077 | C82: FDS002 | D82: =IFERROR(INDEX(Products!$B$6:$B$60,MATCH(C82,Products!$A$6:$A$60,0)),"") -> Tomato Paste 70g Sachet | E82: =IFERROR(INDEX(Products!$C$6:$C$60,MATCH(C82,Products!$A$6:$A$60,0)),"") -> Packaged Food | F82: Sales Return | G82: 1 | H82: Alhaji Bello Stores, Idumota | J82: =IFERROR(IF(OR(F82="Sale",F82="Sales Return"),INDEX(Products!$G$6:$G$60,MATCH(C82,Products!$A$6:$A$60,0)),INDEX(Products!$F$6:$F$60,MATCH(C82,Products!$A$6:$A$60,0))),0) -> 17200 | K82: =G82*J82 -> 17200 | L82: Torn sachets
A83: 46316 | B83: TX-0078 | C83: NDL001 | D83: =IFERROR(INDEX(Products!$B$6:$B$60,MATCH(C83,Products!$A$6:$A$60,0)),"") -> Instant Noodles Chicken 70g | E83: =IFERROR(INDEX(Products!$C$6:$C$60,MATCH(C83,Products!$A$6:$A$60,0)),"") -> Noodles & Pasta | F83: Sales Return | G83: 2 | H83: Mama Chidi Provisions, Mushin | J83: =IFERROR(IF(OR(F83="Sale",F83="Sales Return"),INDEX(Products!$G$6:$G$60,MATCH(C83,Products!$A$6:$A$60,0)),INDEX(Products!$F$6:$F$60,MATCH(C83,Products!$A$6:$A$60,0))),0) -> 8400 | K83: =G83*J83 -> 16800 | L83: Customer returned: short-dated cartons
A84: 46316 | B84: TX-0079 | C84: BEV001 | D84: =IFERROR(INDEX(Products!$B$6:$B$60,MATCH(C84,Products!$A$6:$A$60,0)),"") -> Cola Soft Drink 50cl PET | E84: =IFERROR(INDEX(Products!$C$6:$C$60,MATCH(C84,Products!$A$6:$A$60,0)),"") -> Beverages | F84: Sale | G84: 2 | H84: Sunrise Supermarket, Yaba | I84: Credit | J84: =IFERROR(IF(OR(F84="Sale",F84="Sales Return"),INDEX(Products!$G$6:$G$60,MATCH(C84,Products!$A$6:$A$60,0)),INDEX(Products!$F$6:$F$60,MATCH(C84,Products!$A$6:$A$60,0))),0) -> 5900 | K84: =G84*J84 -> 11800
A85: 46316 | B85: TX-0080 | C85: BEV001 | D85: =IFERROR(INDEX(Products!$B$6:$B$60,MATCH(C85,Products!$A$6:$A$60,0)),"") -> Cola Soft Drink 50cl PET | E85: =IFERROR(INDEX(Products!$C$6:$C$60,MATCH(C85,Products!$A$6:$A$60,0)),"") -> Beverages | F85: Sale | G85: 1 | H85: Balogun Market Stall 14, Lagos Island | I85: Transfer | J85: =IFERROR(IF(OR(F85="Sale",F85="Sales Return"),INDEX(Products!$G$6:$G$60,MATCH(C85,Products!$A$6:$A$60,0)),INDEX(Products!$F$6:$F$60,MATCH(C85,Products!$A$6:$A$60,0))),0) -> 5900 | K85: =G85*J85 -> 5900
A86: 46316 | B86: TX-0081 | C86: BEV001 | D86: =IFERROR(INDEX(Products!$B$6:$B$60,MATCH(C86,Products!$A$6:$A$60,0)),"") -> Cola Soft Drink 50cl PET | E86: =IFERROR(INDEX(Products!$C$6:$C$60,MATCH(C86,Products!$A$6:$A$60,0)),"") -> Beverages | F86: Sale | G86: 1 | H86: Mama Chidi Provisions, Mushin | I86: Cash | J86: =IFERROR(IF(OR(F86="Sale",F86="Sales Return"),INDEX(Products!$G$6:$G$60,MATCH(C86,Products!$A$6:$A$60,0)),INDEX(Products!$F$6:$F$60,MATCH(C86,Products!$A$6:$A$60,0))),0) -> 5900 | K86: =G86*J86 -> 5900
A87: 46316 | B87: TX-0082 | C87: BEV002 | D87: =IFERROR(INDEX(Products!$B$6:$B$60,MATCH(C87,Products!$A$6:$A$60,0)),"") -> Orange Soft Drink 50cl PET | E87: =IFERROR(INDEX(Products!$C$6:$C$60,MATCH(C87,Products!$A$6:$A$60,0)),"") -> Beverages | F87: Sale | G87: 5 | H87: Mama Chidi Provisions, Mushin | I87: Transfer | J87: =IFERROR(IF(OR(F87="Sale",F87="Sales Return"),INDEX(Products!$G$6:$G$60,MATCH(C87,Products!$A$6:$A$60,0)),INDEX(Products!$F$6:$F$60,MATCH(C87,Products!$A$6:$A$60,0))),0) -> 5900 | K87: =G87*J87 -> 29500
A88: 46316 | B88: TX-0083 | C88: BEV003 | D88: =IFERROR(INDEX(Products!$B$6:$B$60,MATCH(C88,Products!$A$6:$A$60,0)),"") -> Table Water 75cl | E88: =IFERROR(INDEX(Products!$C$6:$C$60,MATCH(C88,Products!$A$6:$A$60,0)),"") -> Beverages | F88: Sale | G88: 7 | H88: Alhaji Bello Stores, Idumota | I88: Transfer | J88: =IFERROR(IF(OR(F88="Sale",F88="Sales Return"),INDEX(Products!$G$6:$G$60,MATCH(C88,Products!$A$6:$A$60,0)),INDEX(Products!$F$6:$F$60,MATCH(C88,Products!$A$6:$A$60,0))),0) -> 2300 | K88: =G88*J88 -> 16100
A89: 46316 | B89: TX-0084 | C89: DET001 | D89: =IFERROR(INDEX(Products!$B$6:$B$60,MATCH(C89,Products!$A$6:$A$60,0)),"") -> Detergent Powder 900g | E89: =IFERROR(INDEX(Products!$C$6:$C$60,MATCH(C89,Products!$A$6:$A$60,0)),"") -> Home Care | F89: Sale | G89: 2 | H89: Alhaji Bello Stores, Idumota | I89: Transfer | J89: =IFERROR(IF(OR(F89="Sale",F89="Sales Return"),INDEX(Products!$G$6:$G$60,MATCH(C89,Products!$A$6:$A$60,0)),INDEX(Products!$F$6:$F$60,MATCH(C89,Products!$A$6:$A$60,0))),0) -> 16200 | K89: =G89*J89 -> 32400
A90: 46316 | B90: TX-0085 | C90: DET002 | D90: =IFERROR(INDEX(Products!$B$6:$B$60,MATCH(C90,Products!$A$6:$A$60,0)),"") -> Detergent Powder 400g | E90: =IFERROR(INDEX(Products!$C$6:$C$60,MATCH(C90,Products!$A$6:$A$60,0)),"") -> Home Care | F90: Sale | G90: 3 | H90: Madam Ngozi Shop, Oshodi | I90: Credit | J90: =IFERROR(IF(OR(F90="Sale",F90="Sales Return"),INDEX(Products!$G$6:$G$60,MATCH(C90,Products!$A$6:$A$60,0)),INDEX(Products!$F$6:$F$60,MATCH(C90,Products!$A$6:$A$60,0))),0) -> 19000 | K90: =G90*J90 -> 57000
A91: 46316 | B91: TX-0086 | C91: FDS002 | D91: =IFERROR(INDEX(Products!$B$6:$B$60,MATCH(C91,Products!$A$6:$A$60,0)),"") -> Tomato Paste 70g Sachet | E91: =IFERROR(INDEX(Products!$C$6:$C$60,MATCH(C91,Products!$A$6:$A$60,0)),"") -> Packaged Food | F91: Sale | G91: 2 | H91: Ebenezer Provision Store, Ajegunle | I91: Cash | J91: =IFERROR(IF(OR(F91="Sale",F91="Sales Return"),INDEX(Products!$G$6:$G$60,MATCH(C91,Products!$A$6:$A$60,0)),INDEX(Products!$F$6:$F$60,MATCH(C91,Products!$A$6:$A$60,0))),0) -> 17200 | K91: =G91*J91 -> 34400
A92: 46316 | B92: TX-0087 | C92: FDS003 | D92: =IFERROR(INDEX(Products!$B$6:$B$60,MATCH(C92,Products!$A$6:$A$60,0)),"") -> Seasoning Cubes | E92: =IFERROR(INDEX(Products!$C$6:$C$60,MATCH(C92,Products!$A$6:$A$60,0)),"") -> Packaged Food | F92: Sale | G92: 1 | H92: Alhaji Bello Stores, Idumota | I92: Transfer | J92: =IFERROR(IF(OR(F92="Sale",F92="Sales Return"),INDEX(Products!$G$6:$G$60,MATCH(C92,Products!$A$6:$A$60,0)),INDEX(Products!$F$6:$F$60,MATCH(C92,Products!$A$6:$A$60,0))),0) -> 15500 | K92: =G92*J92 -> 15500
A93: 46316 | B93: TX-0088 | C93: FDS003 | D93: =IFERROR(INDEX(Products!$B$6:$B$60,MATCH(C93,Products!$A$6:$A$60,0)),"") -> Seasoning Cubes | E93: =IFERROR(INDEX(Products!$C$6:$C$60,MATCH(C93,Products!$A$6:$A$60,0)),"") -> Packaged Food | F93: Sale | G93: 3 | H93: Mama Chidi Provisions, Mushin | I93: Cash | J93: =IFERROR(IF(OR(F93="Sale",F93="Sales Return"),INDEX(Products!$G$6:$G$60,MATCH(C93,Products!$A$6:$A$60,0)),INDEX(Products!$F$6:$F$60,MATCH(C93,Products!$A$6:$A$60,0))),0) -> 15500 | K93: =G93*J93 -> 46500
A94: 46316 | B94: TX-0089 | C94: FDS004 | D94: =IFERROR(INDEX(Products!$B$6:$B$60,MATCH(C94,Products!$A$6:$A$60,0)),"") -> Granulated Sugar 500g | E94: =IFERROR(INDEX(Products!$C$6:$C$60,MATCH(C94,Products!$A$6:$A$60,0)),"") -> Packaged Food | F94: Sale | G94: 8 | H94: Greenfield Supermarket, Ikeja | I94: Credit | J94: =IFERROR(IF(OR(F94="Sale",F94="Sales Return"),INDEX(Products!$G$6:$G$60,MATCH(C94,Products!$A$6:$A$60,0)),INDEX(Products!$F$6:$F$60,MATCH(C94,Products!$A$6:$A$60,0))),0) -> 18800 | K94: =G94*J94 -> 150400
A95: 46316 | B95: TX-0090 | C95: NDL001 | D95: =IFERROR(INDEX(Products!$B$6:$B$60,MATCH(C95,Products!$A$6:$A$60,0)),"") -> Instant Noodles Chicken 70g | E95: =IFERROR(INDEX(Products!$C$6:$C$60,MATCH(C95,Products!$A$6:$A$60,0)),"") -> Noodles & Pasta | F95: Sale | G95: 16 | H95: Alhaji Bello Stores, Idumota | I95: Credit | J95: =IFERROR(IF(OR(F95="Sale",F95="Sales Return"),INDEX(Products!$G$6:$G$60,MATCH(C95,Products!$A$6:$A$60,0)),INDEX(Products!$F$6:$F$60,MATCH(C95,Products!$A$6:$A$60,0))),0) -> 8400 | K95: =G95*J95 -> 134400
... A100: 46316 | B100: TX-0095 | C100: OIL002 | D100: =IFERROR(INDEX(Products!$B$6:$B$60,MATCH(C100,Products!$A$6:$A$60,0)),"") -> Vegetable Oil 1L | E100: =IFERROR(INDEX(Products!$C$6:$C$60,MATCH(C100,Products!$A$6:$A$60,0)),"") -> Cooking Oil | F100: Sale | G100: 2 | H100: Alhaji Bello Stores, Idumota | I100: Transfer | J100: =IFERROR(IF(OR(F100="Sale",F100="Sales Return"),INDEX(Products!$G$6:$G$60,MATCH(C100,Products!$A$6:$A$60,0)),INDEX(Products!$F$6:$F$60,MATCH(C100,Products!$A$6:$A$60,0))),0) -> 39000 | K100: =G100*J100 -> 78000
A101: 46316 | B101: TX-0096 | C101: BEV003 | D101: =IFERROR(INDEX(Products!$B$6:$B$60,MATCH(C101,Products!$A$6:$A$60,0)),"") -> Table Water 75cl | E101: =IFERROR(INDEX(Products!$C$6:$C$60,MATCH(C101,Products!$A$6:$A$60,0)),"") -> Beverages | F101: Damaged | G101: 1 | H101: Warehouse | J101: =IFERROR(IF(OR(F101="Sale",F101="Sales Return"),INDEX(Products!$G$6:$G$60,MATCH(C101,Products!$A$6:$A$60,0)),INDEX(Products!$F$6:$F$60,MATCH(C101,Products!$A$6:$A$60,0))),0) -> 1900 | K101: =G101*J101 -> 1900 | L101: Water damage in store
A102: 46316 | B102: TX-0097 | C102: NDL002 | D102: =IFERROR(INDEX(Products!$B$6:$B$60,MATCH(C102,Products!$A$6:$A$60,0)),"") -> Instant Noodles Onion 70g | E102: =IFERROR(INDEX(Products!$C$6:$C$60,MATCH(C102,Products!$A$6:$A$60,0)),"") -> Noodles & Pasta | F102: Supplier Return | G102: 2 | H102: Mushin Noodles & Foods Ltd | J102: =IFERROR(IF(OR(F102="Sale",F102="Sales Return"),INDEX(Products!$G$6:$G$60,MATCH(C102,Products!$A$6:$A$60,0)),INDEX(Products!$F$6:$F$60,MATCH(C102,Products!$A$6:$A$60,0))),0) -> 7700 | K102: =G102*J102 -> 15400 | L102: Short-dated batch returned to supplier
A103: 46317 | B103: TX-0098 | C103: FDS001 | D103: =IFERROR(INDEX(Products!$B$6:$B$60,MATCH(C103,Products!$A$6:$A$60,0)),"") -> Evaporated Milk 160g Tin | E103: =IFERROR(INDEX(Products!$C$6:$C$60,MATCH(C103,Products!$A$6:$A$60,0)),"") -> Packaged Food | F103: Sales Return | G103: 1 | H103: Mama Chidi Provisions, Mushin | J103: =IFERROR(IF(OR(F103="Sale",F103="Sales Return"),INDEX(Products!$G$6:$G$60,MATCH(C103,Products!$A$6:$A$60,0)),INDEX(Products!$F$6:$F$60,MATCH(C103,Products!$A$6:$A$60,0))),0) -> 31000 | K103: =G103*J103 -> 31000 | L103: Dented tins
A104: 46317 | B104: TX-0099 | C104: OIL001 | D104: =IFERROR(INDEX(Products!$B$6:$B$60,MATCH(C104,Products!$A$6:$A$60,0)),"") -> Vegetable Oil 5L | E104: =IFERROR(INDEX(Products!$C$6:$C$60,MATCH(C104,Products!$A$6:$A$60,0)),"") -> Cooking Oil | F104: Sales Return | G104: 1 | H104: Madam Ngozi Shop, Oshodi | J104: =IFERROR(IF(OR(F104="Sale",F104="Sales Return"),INDEX(Products!$G$6:$G$60,MATCH(C104,Products!$A$6:$A$60,0)),INDEX(Products!$F$6:$F$60,MATCH(C104,Products!$A$6:$A$60,0))),0) -> 41500 | K104: =G104*J104 -> 41500 | L104: Leaking 5L container
A105: 46317 | B105: TX-0100 | C105: BEV001 | D105: =IFERROR(INDEX(Products!$B$6:$B$60,MATCH(C105,Products!$A$6:$A$60,0)),"") -> Cola Soft Drink 50cl PET | E105: =IFERROR(INDEX(Products!$C$6:$C$60,MATCH(C105,Products!$A$6:$A$60,0)),"") -> Beverages | F105: Sale | G105: 8 | H105: Madam Ngozi Shop, Oshodi | I105: Cash | J105: =IFERROR(IF(OR(F105="Sale",F105="Sales Return"),INDEX(Products!$G$6:$G$60,MATCH(C105,Products!$A$6:$A$60,0)),INDEX(Products!$F$6:$F$60,MATCH(C105,Products!$A$6:$A$60,0))),0) -> 5900 | K105: =G105*J105 -> 47200
A106: 46317 | B106: TX-0101 | C106: BEV001 | D106: =IFERROR(INDEX(Products!$B$6:$B$60,MATCH(C106,Products!$A$6:$A$60,0)),"") -> Cola Soft Drink 50cl PET | E106: =IFERROR(INDEX(Products!$C$6:$C$60,MATCH(C106,Products!$A$6:$A$60,0)),"") -> Beverages | F106: Sale | G106: 2 | H106: Oluwaseun Mini-Mart, Surulere | I106: Cash | J106: =IFERROR(IF(OR(F106="Sale",F106="Sales Return"),INDEX(Products!$G$6:$G$60,MATCH(C106,Products!$A$6:$A$60,0)),INDEX(Products!$F$6:$F$60,MATCH(C106,Products!$A$6:$A$60,0))),0) -> 5900 | K106: =G106*J106 -> 11800
A107: 46317 | B107: TX-0102 | C107: BEV001 | D107: =IFERROR(INDEX(Products!$B$6:$B$60,MATCH(C107,Products!$A$6:$A$60,0)),"") -> Cola Soft Drink 50cl PET | E107: =IFERROR(INDEX(Products!$C$6:$C$60,MATCH(C107,Products!$A$6:$A$60,0)),"") -> Beverages | F107: Sale | G107: 5 | H107: Madam Ngozi Shop, Oshodi | I107: Cash | J107: =IFERROR(IF(OR(F107="Sale",F107="Sales Return"),INDEX(Products!$G$6:$G$60,MATCH(C107,Products!$A$6:$A$60,0)),INDEX(Products!$F$6:$F$60,MATCH(C107,Products!$A$6:$A$60,0))),0) -> 5900 | K107: =G107*J107 -> 29500
A108: 46317 | B108: TX-0103 | C108: BEV002 | D108: =IFERROR(INDEX(Products!$B$6:$B$60,MATCH(C108,Products!$A$6:$A$60,0)),"") -> Orange Soft Drink 50cl PET | E108: =IFERROR(INDEX(Products!$C$6:$C$60,MATCH(C108,Products!$A$6:$A$60,0)),"") -> Beverages | F108: Sale | G108: 6 | H108: Balogun Market Stall 14, Lagos Island | I108: Cash | J108: =IFERROR(IF(OR(F108="Sale",F108="Sales Return"),INDEX(Products!$G$6:$G$60,MATCH(C108,Products!$A$6:$A$60,0)),INDEX(Products!$F$6:$F$60,MATCH(C108,Products!$A$6:$A$60,0))),0) -> 5900 | K108: =G108*J108 -> 35400
A109: 46317 | B109: TX-0104 | C109: BEV002 | D109: =IFERROR(INDEX(Products!$B$6:$B$60,MATCH(C109,Products!$A$6:$A$60,0)),"") -> Orange Soft Drink 50cl PET | E109: =IFERROR(INDEX(Products!$C$6:$C$60,MATCH(C109,Products!$A$6:$A$60,0)),"") -> Beverages | F109: Sale | G109: 2 | H109: Alhaji Bello Stores, Idumota | I109: Transfer | J109: =IFERROR(IF(OR(F109="Sale",F109="Sales Return"),INDEX(Products!$G$6:$G$60,MATCH(C109,Products!$A$6:$A$60,0)),INDEX(Products!$F$6:$F$60,MATCH(C109,Products!$A$6:$A$60,0))),0) -> 5900 | K109: =G109*J109 -> 11800
A110: 46317 | B110: TX-0105 | C110: BEV003 | D110: =IFERROR(INDEX(Products!$B$6:$B$60,MATCH(C110,Products!$A$6:$A$60,0)),"") -> Table Water 75cl | E110: =IFERROR(INDEX(Products!$C$6:$C$60,MATCH(C110,Products!$A$6:$A$60,0)),"") -> Beverages | F110: Sale | G110: 6 | H110: Madam Ngozi Shop, Oshodi | I110: Transfer | J110: =IFERROR(IF(OR(F110="Sale",F110="Sales Return"),INDEX(Products!$G$6:$G$60,MATCH(C110,Products!$A$6:$A$60,0)),INDEX(Products!$F$6:$F$60,MATCH(C110,Products!$A$6:$A$60,0))),0) -> 2300 | K110: =G110*J110 -> 13800
A111: 46317 | B111: TX-0106 | C111: BEV003 | D111: =IFERROR(INDEX(Products!$B$6:$B$60,MATCH(C111,Products!$A$6:$A$60,0)),"") -> Table Water 75cl | E111: =IFERROR(INDEX(Products!$C$6:$C$60,MATCH(C111,Products!$A$6:$A$60,0)),"") -> Beverages | F111: Sale | G111: 5 | H111: Mama Chidi Provisions, Mushin | I111: Credit | J111: =IFERROR(IF(OR(F111="Sale",F111="Sales Return"),INDEX(Products!$G$6:$G$60,MATCH(C111,Products!$A$6:$A$60,0)),INDEX(Products!$F$6:$F$60,MATCH(C111,Products!$A$6:$A$60,0))),0) -> 2300 | K111: =G111*J111 -> 11500
A112: 46317 | B112: TX-0107 | C112: BEV003 | D112: =IFERROR(INDEX(Products!$B$6:$B$60,MATCH(C112,Products!$A$6:$A$60,0)),"") -> Table Water 75cl | E112: =IFERROR(INDEX(Products!$C$6:$C$60,MATCH(C112,Products!$A$6:$A$60,0)),"") -> Beverages | F112: Sale | G112: 1 | H112: Ebenezer Provision Store, Ajegunle | I112: Credit | J112: =IFERROR(IF(OR(F112="Sale",F112="Sales Return"),INDEX(Products!$G$6:$G$60,MATCH(C112,Products!$A$6:$A$60,0)),INDEX(Products!$F$6:$F$60,MATCH(C112,Products!$A$6:$A$60,0))),0) -> 2300 | K112: =G112*J112 -> 2300
A113: 46317 | B113: TX-0108 | C113: BEV004 | D113: =IFERROR(INDEX(Products!$B$6:$B$60,MATCH(C113,Products!$A$6:$A$60,0)),"") -> Malt Drink 33cl Can | E113: =IFERROR(INDEX(Products!$C$6:$C$60,MATCH(C113,Products!$A$6:$A$60,0)),"") -> Beverages | F113: Sale | G113: 1 | H113: Greenfield Supermarket, Ikeja | I113: Credit | J113: =IFERROR(IF(OR(F113="Sale",F113="Sales Return"),INDEX(Products!$G$6:$G$60,MATCH(C113,Products!$A$6:$A$60,0)),INDEX(Products!$F$6:$F$60,MATCH(C113,Products!$A$6:$A$60,0))),0) -> 11200 | K113: =G113*J113 -> 11200
A114: 46317 | B114: TX-0109 | C114: DET001 | D114: =IFERROR(INDEX(Products!$B$6:$B$60,MATCH(C114,Products!$A$6:$A$60,0)),"") -> Detergent Powder 900g | E114: =IFERROR(INDEX(Products!$C$6:$C$60,MATCH(C114,Products!$A$6:$A$60,0)),"") -> Home Care | F114: Sale | G114: 2 | H114: Ebenezer Provision Store, Ajegunle | I114: Cash | J114: =IFERROR(IF(OR(F114="Sale",F114="Sales Return"),INDEX(Products!$G$6:$G$60,MATCH(C114,Products!$A$6:$A$60,0)),INDEX(Products!$F$6:$F$60,MATCH(C114,Products!$A$6:$A$60,0))),0) -> 16200 | K114: =G114*J114 -> 32400
A115: 46317 | B115: TX-0110 | C115: DET002 | D115: =IFERROR(INDEX(Products!$B$6:$B$60,MATCH(C115,Products!$A$6:$A$60,0)),"") -> Detergent Powder 400g | E115: =IFERROR(INDEX(Products!$C$6:$C$60,MATCH(C115,Products!$A$6:$A$60,0)),"") -> Home Care | F115: Sale | G115: 2 | H115: Sunrise Supermarket, Yaba | I115: Transfer | J115: =IFERROR(IF(OR(F115="Sale",F115="Sales Return"),INDEX(Products!$G$6:$G$60,MATCH(C115,Products!$A$6:$A$60,0)),INDEX(Products!$F$6:$F$60,MATCH(C115,Products!$A$6:$A$60,0))),0) -> 19000 | K115: =G115*J115 -> 38000
A116: 46317 | B116: TX-0111 | C116: DET003 | D116: =IFERROR(INDEX(Products!$B$6:$B$60,MATCH(C116,Products!$A$6:$A$60,0)),"") -> Laundry Bar Soap | E116: =IFERROR(INDEX(Products!$C$6:$C$60,MATCH(C116,Products!$A$6:$A$60,0)),"") -> Home Care | F116: Sale | G116: 3 | H116: Oluwaseun Mini-Mart, Surulere | I116: Cash | J116: =IFERROR(IF(OR(F116="Sale",F116="Sales Return"),INDEX(Products!$G$6:$G$60,MATCH(C116,Products!$A$6:$A$60,0)),INDEX(Products!$F$6:$F$60,MATCH(C116,Products!$A$6:$A$60,0))),0) -> 10200 | K116: =G116*J116 -> 30600
... A133: 46317 | B133: TX-0128 | C133: OIL002 | D133: =IFERROR(INDEX(Products!$B$6:$B$60,MATCH(C133,Products!$A$6:$A$60,0)),"") -> Vegetable Oil 1L | E133: =IFERROR(INDEX(Products!$C$6:$C$60,MATCH(C133,Products!$A$6:$A$60,0)),"") -> Cooking Oil | F133: Sale | G133: 2 | H133: Sunrise Supermarket, Yaba | I133: Credit | J133: =IFERROR(IF(OR(F133="Sale",F133="Sales Return"),INDEX(Products!$G$6:$G$60,MATCH(C133,Products!$A$6:$A$60,0)),INDEX(Products!$F$6:$F$60,MATCH(C133,Products!$A$6:$A$60,0))),0) -> 39000 | K133: =G133*J133 -> 78000
A134: 46317 | B134: TX-0129 | C134: FDS002 | D134: =IFERROR(INDEX(Products!$B$6:$B$60,MATCH(C134,Products!$A$6:$A$60,0)),"") -> Tomato Paste 70g Sachet | E134: =IFERROR(INDEX(Products!$C$6:$C$60,MATCH(C134,Products!$A$6:$A$60,0)),"") -> Packaged Food | F134: Damaged | G134: 2 | H134: Warehouse | J134: =IFERROR(IF(OR(F134="Sale",F134="Sales Return"),INDEX(Products!$G$6:$G$60,MATCH(C134,Products!$A$6:$A$60,0)),INDEX(Products!$F$6:$F$60,MATCH(C134,Products!$A$6:$A$60,0))),0) -> 15500 | K134: =G134*J134 -> 31000 | L134: Torn sachets
A135: 46317 | B135: TX-0130 | C135: NDL001 | D135: =IFERROR(INDEX(Products!$B$6:$B$60,MATCH(C135,Products!$A$6:$A$60,0)),"") -> Instant Noodles Chicken 70g | E135: =IFERROR(INDEX(Products!$C$6:$C$60,MATCH(C135,Products!$A$6:$A$60,0)),"") -> Noodles & Pasta | F135: Damaged | G135: 2 | H135: Warehouse | J135: =IFERROR(IF(OR(F135="Sale",F135="Sales Return"),INDEX(Products!$G$6:$G$60,MATCH(C135,Products!$A$6:$A$60,0)),INDEX(Products!$F$6:$F$60,MATCH(C135,Products!$A$6:$A$60,0))),0) -> 7600 | K135: =G135*J135 -> 15200 | L135: Crushed cartons in stacking
A136: 46318 | B136: TX-0131 | C136: BEV001 | D136: =IFERROR(INDEX(Products!$B$6:$B$60,MATCH(C136,Products!$A$6:$A$60,0)),"") -> Cola Soft Drink 50cl PET | E136: =IFERROR(INDEX(Products!$C$6:$C$60,MATCH(C136,Products!$A$6:$A$60,0)),"") -> Beverages | F136: Sales Return | G136: 2 | H136: Ebenezer Provision Store, Ajegunle | J136: =IFERROR(IF(OR(F136="Sale",F136="Sales Return"),INDEX(Products!$G$6:$G$60,MATCH(C136,Products!$A$6:$A$60,0)),INDEX(Products!$F$6:$F$60,MATCH(C136,Products!$A$6:$A$60,0))),0) -> 5900 | K136: =G136*J136 -> 11800 | L136: Unsold stock returned by retailer
A137: 46318 | B137: TX-0132 | C137: BEV001 | D137: =IFERROR(INDEX(Products!$B$6:$B$60,MATCH(C137,Products!$A$6:$A$60,0)),"") -> Cola Soft Drink 50cl PET | E137: =IFERROR(INDEX(Products!$C$6:$C$60,MATCH(C137,Products!$A$6:$A$60,0)),"") -> Beverages | F137: Sale | G137: 13 | H137: Sunrise Supermarket, Yaba | I137: Credit | J137: =IFERROR(IF(OR(F137="Sale",F137="Sales Return"),INDEX(Products!$G$6:$G$60,MATCH(C137,Products!$A$6:$A$60,0)),INDEX(Products!$F$6:$F$60,MATCH(C137,Products!$A$6:$A$60,0))),0) -> 5900 | K137: =G137*J137 -> 76700
A138: 46318 | B138: TX-0133 | C138: BEV001 | D138: =IFERROR(INDEX(Products!$B$6:$B$60,MATCH(C138,Products!$A$6:$A$60,0)),"") -> Cola Soft Drink 50cl PET | E138: =IFERROR(INDEX(Products!$C$6:$C$60,MATCH(C138,Products!$A$6:$A$60,0)),"") -> Beverages | F138: Sale | G138: 1 | H138: Mama Chidi Provisions, Mushin | I138: Credit | J138: =IFERROR(IF(OR(F138="Sale",F138="Sales Return"),INDEX(Products!$G$6:$G$60,MATCH(C138,Products!$A$6:$A$60,0)),INDEX(Products!$F$6:$F$60,MATCH(C138,Products!$A$6:$A$60,0))),0) -> 5900 | K138: =G138*J138 -> 5900
A139: 46318 | B139: TX-0134 | C139: BEV002 | D139: =IFERROR(INDEX(Products!$B$6:$B$60,MATCH(C139,Products!$A$6:$A$60,0)),"") -> Orange Soft Drink 50cl PET | E139: =IFERROR(INDEX(Products!$C$6:$C$60,MATCH(C139,Products!$A$6:$A$60,0)),"") -> Beverages | F139: Sale | G139: 5 | H139: Greenfield Supermarket, Ikeja | I139: Credit | J139: =IFERROR(IF(OR(F139="Sale",F139="Sales Return"),INDEX(Products!$G$6:$G$60,MATCH(C139,Products!$A$6:$A$60,0)),INDEX(Products!$F$6:$F$60,MATCH(C139,Products!$A$6:$A$60,0))),0) -> 5900 | K139: =G139*J139 -> 29500
A140: 46318 | B140: TX-0135 | C140: BEV002 | D140: =IFERROR(INDEX(Products!$B$6:$B$60,MATCH(C140,Products!$A$6:$A$60,0)),"") -> Orange Soft Drink 50cl PET | E140: =IFERROR(INDEX(Products!$C$6:$C$60,MATCH(C140,Products!$A$6:$A$60,0)),"") -> Beverages | F140: Sale | G140: 2 | H140: Oluwaseun Mini-Mart, Surulere | I140: Cash | J140: =IFERROR(IF(OR(F140="Sale",F140="Sales Return"),INDEX(Products!$G$6:$G$60,MATCH(C140,Products!$A$6:$A$60,0)),INDEX(Products!$F$6:$F$60,MATCH(C140,Products!$A$6:$A$60,0))),0) -> 5900 | K140: =G140*J140 -> 11800
A141: 46318 | B141: TX-0136 | C141: BEV003 | D141: =IFERROR(INDEX(Products!$B$6:$B$60,MATCH(C141,Products!$A$6:$A$60,0)),"") -> Table Water 75cl | E141: =IFERROR(INDEX(Products!$C$6:$C$60,MATCH(C141,Products!$A$6:$A$60,0)),"") -> Beverages | F141: Sale | G141: 7 | H141: Alhaji Bello Stores, Idumota | I141: Transfer | J141: =IFERROR(IF(OR(F141="Sale",F141="Sales Return"),INDEX(Products!$G$6:$G$60,MATCH(C141,Products!$A$6:$A$60,0)),INDEX(Products!$F$6:$F$60,MATCH(C141,Products!$A$6:$A$60,0))),0) -> 2300 | K141: =G141*J141 -> 16100
A142: 46318 | B142: TX-0137 | C142: BEV003 | D142: =IFERROR(INDEX(Products!$B$6:$B$60,MATCH(C142,Products!$A$6:$A$60,0)),"") -> Table Water 75cl | E142: =IFERROR(INDEX(Products!$C$6:$C$60,MATCH(C142,Products!$A$6:$A$60,0)),"") -> Beverages | F142: Sale | G142: 1 | H142: Balogun Market Stall 14, Lagos Island | I142: Cash | J142: =IFERROR(IF(OR(F142="Sale",F142="Sales Return"),INDEX(Products!$G$6:$G$60,MATCH(C142,Products!$A$6:$A$60,0)),INDEX(Products!$F$6:$F$60,MATCH(C142,Products!$A$6:$A$60,0))),0) -> 2300 | K142: =G142*J142 -> 2300
A143: 46318 | B143: TX-0138 | C143: BEV003 | D143: =IFERROR(INDEX(Products!$B$6:$B$60,MATCH(C143,Products!$A$6:$A$60,0)),"") -> Table Water 75cl | E143: =IFERROR(INDEX(Products!$C$6:$C$60,MATCH(C143,Products!$A$6:$A$60,0)),"") -> Beverages | F143: Sale | G143: 5 | H143: Ebenezer Provision Store, Ajegunle | I143: Cash | J143: =IFERROR(IF(OR(F143="Sale",F143="Sales Return"),INDEX(Products!$G$6:$G$60,MATCH(C143,Products!$A$6:$A$60,0)),INDEX(Products!$F$6:$F$60,MATCH(C143,Products!$A$6:$A$60,0))),0) -> 2300 | K143: =G143*J143 -> 11500
A144: 46318 | B144: TX-0139 | C144: BEV004 | D144: =IFERROR(INDEX(Products!$B$6:$B$60,MATCH(C144,Products!$A$6:$A$60,0)),"") -> Malt Drink 33cl Can | E144: =IFERROR(INDEX(Products!$C$6:$C$60,MATCH(C144,Products!$A$6:$A$60,0)),"") -> Beverages | F144: Sale | G144: 1 | H144: Mama Chidi Provisions, Mushin | I144: Transfer | J144: =IFERROR(IF(OR(F144="Sale",F144="Sales Return"),INDEX(Products!$G$6:$G$60,MATCH(C144,Products!$A$6:$A$60,0)),INDEX(Products!$F$6:$F$60,MATCH(C144,Products!$A$6:$A$60,0))),0) -> 11200 | K144: =G144*J144 -> 11200
A145: 46318 | B145: TX-0140 | C145: DET001 | D145: =IFERROR(INDEX(Products!$B$6:$B$60,MATCH(C145,Products!$A$6:$A$60,0)),"") -> Detergent Powder 900g | E145: =IFERROR(INDEX(Products!$C$6:$C$60,MATCH(C145,Products!$A$6:$A$60,0)),"") -> Home Care | F145: Sale | G145: 5 | H145: Alhaji Bello Stores, Idumota | I145: Credit | J145: =IFERROR(IF(OR(F145="Sale",F145="Sales Return"),INDEX(Products!$G$6:$G$60,MATCH(C145,Products!$A$6:$A$60,0)),INDEX(Products!$F$6:$F$60,MATCH(C145,Products!$A$6:$A$60,0))),0) -> 16200 | K145: =G145*J145 -> 81000
A146: 46318 | B146: TX-0141 | C146: DET001 | D146: =IFERROR(INDEX(Products!$B$6:$B$60,MATCH(C146,Products!$A$6:$A$60,0)),"") -> Detergent Powder 900g | E146: =IFERROR(INDEX(Products!$C$6:$C$60,MATCH(C146,Products!$A$6:$A$60,0)),"") -> Home Care | F146: Sale | G146: 2 | H146: Balogun Market Stall 14, Lagos Island | I146: Cash | J146: =IFERROR(IF(OR(F146="Sale",F146="Sales Return"),INDEX(Products!$G$6:$G$60,MATCH(C146,Products!$A$6:$A$60,0)),INDEX(Products!$F$6:$F$60,MATCH(C146,Products!$A$6:$A$60,0))),0) -> 16200 | K146: =G146*J146 -> 32400
A147: 46318 | B147: TX-0142 | C147: DET001 | D147: =IFERROR(INDEX(Products!$B$6:$B$60,MATCH(C147,Products!$A$6:$A$60,0)),"") -> Detergent Powder 900g | E147: =IFERROR(INDEX(Products!$C$6:$C$60,MATCH(C147,Products!$A$6:$A$60,0)),"") -> Home Care | F147: Sale | G147: 1 | H147: Mama Chidi Provisions, Mushin | I147: Cash | J147: =IFERROR(IF(OR(F147="Sale",F147="Sales Return"),INDEX(Products!$G$6:$G$60,MATCH(C147,Products!$A$6:$A$60,0)),INDEX(Products!$F$6:$F$60,MATCH(C147,Products!$A$6:$A$60,0))),0) -> 16200 | K147: =G147*J147 -> 16200
A148: 46318 | B148: TX-0143 | C148: DET002 | D148: =IFERROR(INDEX(Products!$B$6:$B$60,MATCH(C148,Products!$A$6:$A$60,0)),"") -> Detergent Powder 400g | E148: =IFERROR(INDEX(Products!$C$6:$C$60,MATCH(C148,Products!$A$6:$A$60,0)),"") -> Home Care | F148: Sale | G148: 1 | H148: Balogun Market Stall 14, Lagos Island | I148: Cash | J148: =IFERROR(IF(OR(F148="Sale",F148="Sales Return"),INDEX(Products!$G$6:$G$60,MATCH(C148,Products!$A$6:$A$60,0)),INDEX(Products!$F$6:$F$60,MATCH(C148,Products!$A$6:$A$60,0))),0) -> 19000 | K148: =G148*J148 -> 19000
... A169: 46318 | B169: TX-0164 | C169: OIL002 | D169: =IFERROR(INDEX(Products!$B$6:$B$60,MATCH(C169,Products!$A$6:$A$60,0)),"") -> Vegetable Oil 1L | E169: =IFERROR(INDEX(Products!$C$6:$C$60,MATCH(C169,Products!$A$6:$A$60,0)),"") -> Cooking Oil | F169: Sale | G169: 1 | H169: Greenfield Supermarket, Ikeja | I169: Credit | J169: =IFERROR(IF(OR(F169="Sale",F169="Sales Return"),INDEX(Products!$G$6:$G$60,MATCH(C169,Products!$A$6:$A$60,0)),INDEX(Products!$F$6:$F$60,MATCH(C169,Products!$A$6:$A$60,0))),0) -> 39000 | K169: =G169*J169 -> 39000
A170: 46318 | B170: TX-0165 | C170: FDS001 | D170: =IFERROR(INDEX(Products!$B$6:$B$60,MATCH(C170,Products!$A$6:$A$60,0)),"") -> Evaporated Milk 160g Tin | E170: =IFERROR(INDEX(Products!$C$6:$C$60,MATCH(C170,Products!$A$6:$A$60,0)),"") -> Packaged Food | F170: Supplier Return | G170: 1 | H170: Idumota Dry Goods Traders | J170: =IFERROR(IF(OR(F170="Sale",F170="Sales Return"),INDEX(Products!$G$6:$G$60,MATCH(C170,Products!$A$6:$A$60,0)),INDEX(Products!$F$6:$F$60,MATCH(C170,Products!$A$6:$A$60,0))),0) -> 28000 | K170: =G170*J170 -> 28000 | L170: Dented tins, credit note requested
A171: 46318 | B171: TX-0166 | C171: OIL002 | D171: =IFERROR(INDEX(Products!$B$6:$B$60,MATCH(C171,Products!$A$6:$A$60,0)),"") -> Vegetable Oil 1L | E171: =IFERROR(INDEX(Products!$C$6:$C$60,MATCH(C171,Products!$A$6:$A$60,0)),"") -> Cooking Oil | F171: Damaged | G171: 1 | H171: Warehouse | J171: =IFERROR(IF(OR(F171="Sale",F171="Sales Return"),INDEX(Products!$G$6:$G$60,MATCH(C171,Products!$A$6:$A$60,0)),INDEX(Products!$F$6:$F$60,MATCH(C171,Products!$A$6:$A$60,0))),0) -> 36000 | K171: =G171*J171 -> 36000 | L171: Leaking bottles
A172: 46319 | B172: TX-0167 | C172: BEV003 | D172: =IFERROR(INDEX(Products!$B$6:$B$60,MATCH(C172,Products!$A$6:$A$60,0)),"") -> Table Water 75cl | E172: =IFERROR(INDEX(Products!$C$6:$C$60,MATCH(C172,Products!$A$6:$A$60,0)),"") -> Beverages | F172: Sales Return | G172: 2 | H172: Sunrise Supermarket, Yaba | J172: =IFERROR(IF(OR(F172="Sale",F172="Sales Return"),INDEX(Products!$G$6:$G$60,MATCH(C172,Products!$A$6:$A$60,0)),INDEX(Products!$F$6:$F$60,MATCH(C172,Products!$A$6:$A$60,0))),0) -> 2300 | K172: =G172*J172 -> 4600 | L172: Wrong pack size delivered
A173: 46319 | B173: TX-0168 | C173: BEV001 | D173: =IFERROR(INDEX(Products!$B$6:$B$60,MATCH(C173,Products!$A$6:$A$60,0)),"") -> Cola Soft Drink 50cl PET | E173: =IFERROR(INDEX(Products!$C$6:$C$60,MATCH(C173,Products!$A$6:$A$60,0)),"") -> Beverages | F173: Sale | G173: 8 | H173: Alhaji Bello Stores, Idumota | I173: Transfer | J173: =IFERROR(IF(OR(F173="Sale",F173="Sales Return"),INDEX(Products!$G$6:$G$60,MATCH(C173,Products!$A$6:$A$60,0)),INDEX(Products!$F$6:$F$60,MATCH(C173,Products!$A$6:$A$60,0))),0) -> 5900 | K173: =G173*J173 -> 47200
A174: 46319 | B174: TX-0169 | C174: BEV001 | D174: =IFERROR(INDEX(Products!$B$6:$B$60,MATCH(C174,Products!$A$6:$A$60,0)),"") -> Cola Soft Drink 50cl PET | E174: =IFERROR(INDEX(Products!$C$6:$C$60,MATCH(C174,Products!$A$6:$A$60,0)),"") -> Beverages | F174: Sale | G174: 4 | H174: Balogun Market Stall 14, Lagos Island | I174: Cash | J174: =IFERROR(IF(OR(F174="Sale",F174="Sales Return"),INDEX(Products!$G$6:$G$60,MATCH(C174,Products!$A$6:$A$60,0)),INDEX(Products!$F$6:$F$60,MATCH(C174,Products!$A$6:$A$60,0))),0) -> 5900 | K174: =G174*J174 -> 23600
A175: 46319 | B175: TX-0170 | C175: BEV002 | D175: =IFERROR(INDEX(Products!$B$6:$B$60,MATCH(C175,Products!$A$6:$A$60,0)),"") -> Orange Soft Drink 50cl PET | E175: =IFERROR(INDEX(Products!$C$6:$C$60,MATCH(C175,Products!$A$6:$A$60,0)),"") -> Beverages | F175: Sale | G175: 8 | H175: Oluwaseun Mini-Mart, Surulere | I175: Transfer | J175: =IFERROR(IF(OR(F175="Sale",F175="Sales Return"),INDEX(Products!$G$6:$G$60,MATCH(C175,Products!$A$6:$A$60,0)),INDEX(Products!$F$6:$F$60,MATCH(C175,Products!$A$6:$A$60,0))),0) -> 5900 | K175: =G175*J175 -> 47200
...

Sheet Register
A1: Inventory Register
A2: Expected Closing = Opening + Stock Received + Sales Returns − Units Sold − Supplier Returns − Damaged. Blue cells: enter opening stock and physical count.
A3: ="Week: "&TEXT(Settings!B5,"dd mmm yyyy")&" to "&TEXT(Settings!B7,"dd mmm yyyy") -> Week: 19 Oct 2026 to 24 Oct 2026
A5: Product Code | B5: Product Name | C5: Supplier | D5: Opening Stock | E5: Stock Received (Purchases) | F5: Sales Returns | G5: Units Sold | H5: Supplier Returns | I5: Damaged Stock | J5: Expected Closing (Book) | K5: Physical Count | L5: Variance (units) | M5: Unit Cost (₦) | N5: Variance Value (₦) | O5: Variance % | P5: Count Status
A6: =Products!A6 -> BEV001 | B6: =Products!B6 -> Cola Soft Drink 50cl PET | C6: =Products!D6 -> Apapa Beverages Depot | D6: 31 | E6: =SUMIFS(Transactions!$G$6:$G$1000,Transactions!$C$6:$C$1000,$A6,Transactions!$F$6:$F$1000,"Purchase",Transactions!$A$6:$A$1000,">="&Settings!$B$5,Transactions!$A$6:$A$1000,"<="&Settings!$B$7) -> 54 | F6: =SUMIFS(Transactions!$G$6:$G$1000,Transactions!$C$6:$C$1000,$A6,Transactions!$F$6:$F$1000,"Sales Return",Transactions!$A$6:$A$1000,">="&Settings!$B$5,Transactions!$A$6:$A$1000,"<="&Settings!$B$7) -> 2 | G6: =SUMIFS(Transactions!$G$6:$G$1000,Transactions!$C$6:$C$1000,$A6,Transactions!$F$6:$F$1000,"Sale",Transactions!$A$6:$A$1000,">="&Settings!$B$5,Transactions!$A$6:$A$1000,"<="&Settings!$B$7) -> 60 | H6: =SUMIFS(Transactions!$G$6:$G$1000,Transactions!$C$6:$C$1000,$A6,Transactions!$F$6:$F$1000,"Supplier Return",Transactions!$A$6:$A$1000,">="&Settings!$B$5,Transactions!$A$6:$A$1000,"<="&Settings!$B$7) -> 0 | I6: =SUMIFS(Transactions!$G$6:$G$1000,Transactions!$C$6:$C$1000,$A6,Transactions!$F$6:$F$1000,"Damaged",Transactions!$A$6:$A$1000,">="&Settings!$B$5,Transactions!$A$6:$A$1000,"<="&Settings!$B$7) -> 0 | J6: =D6+E6+F6-G6-H6-I6 -> 27 | K6: 25 | L6: =IF(K6="","",K6-J6) -> -2 | M6: =Products!F6 -> 5200 | N6: =IF(L6="","",L6*M6) -> -10400 | O6: =IF(OR(K6="",J6<=0),"",L6/J6) -> -0.074074074 | P6: =IF(K6="","Not counted",IF(L6=0,"Match",IF(L6<0,"Shortage","Overage"))) -> Shortage
A7: =Products!A7 -> BEV002 | B7: =Products!B7 -> Orange Soft Drink 50cl PET | C7: =Products!D7 -> Apapa Beverages Depot | D7: 32 | E7: =SUMIFS(Transactions!$G$6:$G$1000,Transactions!$C$6:$C$1000,$A7,Transactions!$F$6:$F$1000,"Purchase",Transactions!$A$6:$A$1000,">="&Settings!$B$5,Transactions!$A$6:$A$1000,"<="&Settings!$B$7) -> 36 | F7: =SUMIFS(Transactions!$G$6:$G$1000,Transactions!$C$6:$C$1000,$A7,Transactions!$F$6:$F$1000,"Sales Return",Transactions!$A$6:$A$1000,">="&Settings!$B$5,Transactions!$A$6:$A$1000,"<="&Settings!$B$7) -> 0 | G7: =SUMIFS(Transactions!$G$6:$G$1000,Transactions!$C$6:$C$1000,$A7,Transactions!$F$6:$F$1000,"Sale",Transactions!$A$6:$A$1000,">="&Settings!$B$5,Transactions!$A$6:$A$1000,"<="&Settings!$B$7) -> 42 | H7: =SUMIFS(Transactions!$G$6:$G$1000,Transactions!$C$6:$C$1000,$A7,Transactions!$F$6:$F$1000,"Supplier Return",Transactions!$A$6:$A$1000,">="&Settings!$B$5,Transactions!$A$6:$A$1000,"<="&Settings!$B$7) -> 0 | I7: =SUMIFS(Transactions!$G$6:$G$1000,Transactions!$C$6:$C$1000,$A7,Transactions!$F$6:$F$1000,"Damaged",Transactions!$A$6:$A$1000,">="&Settings!$B$5,Transactions!$A$6:$A$1000,"<="&Settings!$B$7) -> 1 | J7: =D7+E7+F7-G7-H7-I7 -> 25 | K7: 25 | L7: =IF(K7="","",K7-J7) -> 0 | M7: =Products!F7 -> 5200 | N7: =IF(L7="","",L7*M7) -> 0 | O7: =IF(OR(K7="",J7<=0),"",L7/J7) -> 0 | P7: =IF(K7="","Not counted",IF(L7=0,"Match",IF(L7<0,"Shortage","Overage"))) -> Match
A8: =Products!A8 -> BEV003 | B8: =Products!B8 -> Table Water 75cl | C8: =Products!D8 -> Apapa Beverages Depot | D8: 64 | E8: =SUMIFS(Transactions!$G$6:$G$1000,Transactions!$C$6:$C$1000,$A8,Transactions!$F$6:$F$1000,"Purchase",Transactions!$A$6:$A$1000,">="&Settings!$B$5,Transactions!$A$6:$A$1000,"<="&Settings!$B$7) -> 66 | F8: =SUMIFS(Transactions!$G$6:$G$1000,Transactions!$C$6:$C$1000,$A8,Transactions!$F$6:$F$1000,"Sales Return",Transactions!$A$6:$A$1000,">="&Settings!$B$5,Transactions!$A$6:$A$1000,"<="&Settings!$B$7) -> 2 | G8: =SUMIFS(Transactions!$G$6:$G$1000,Transactions!$C$6:$C$1000,$A8,Transactions!$F$6:$F$1000,"Sale",Transactions!$A$6:$A$1000,">="&Settings!$B$5,Transactions!$A$6:$A$1000,"<="&Settings!$B$7) -> 72 | H8: =SUMIFS(Transactions!$G$6:$G$1000,Transactions!$C$6:$C$1000,$A8,Transactions!$F$6:$F$1000,"Supplier Return",Transactions!$A$6:$A$1000,">="&Settings!$B$5,Transactions!$A$6:$A$1000,"<="&Settings!$B$7) -> 0 | I8: =SUMIFS(Transactions!$G$6:$G$1000,Transactions!$C$6:$C$1000,$A8,Transactions!$F$6:$F$1000,"Damaged",Transactions!$A$6:$A$1000,">="&Settings!$B$5,Transactions!$A$6:$A$1000,"<="&Settings!$B$7) -> 1 | J8: =D8+E8+F8-G8-H8-I8 -> 59 | K8: 55 | L8: =IF(K8="","",K8-J8) -> -4 | M8: =Products!F8 -> 1900 | N8: =IF(L8="","",L8*M8) -> -7600 | O8: =IF(OR(K8="",J8<=0),"",L8/J8) -> -0.06779661 | P8: =IF(K8="","Not counted",IF(L8=0,"Match",IF(L8<0,"Shortage","Overage"))) -> Shortage
A9: =Products!A9 -> BEV004 | B9: =Products!B9 -> Malt Drink 33cl Can | C9: =Products!D9 -> Apapa Beverages Depot | D9: 37 | E9: =SUMIFS(Transactions!$G$6:$G$1000,Transactions!$C$6:$C$1000,$A9,Transactions!$F$6:$F$1000,"Purchase",Transactions!$A$6:$A$1000,">="&Settings!$B$5,Transactions!$A$6:$A$1000,"<="&Settings!$B$7) -> 0 | F9: =SUMIFS(Transactions!$G$6:$G$1000,Transactions!$C$6:$C$1000,$A9,Transactions!$F$6:$F$1000,"Sales Return",Transactions!$A$6:$A$1000,">="&Settings!$B$5,Transactions!$A$6:$A$1000,"<="&Settings!$B$7) -> 0 | G9: =SUMIFS(Transactions!$G$6:$G$1000,Transactions!$C$6:$C$1000,$A9,Transactions!$F$6:$F$1000,"Sale",Transactions!$A$6:$A$1000,">="&Settings!$B$5,Transactions!$A$6:$A$1000,"<="&Settings!$B$7) -> 9 | H9: =SUMIFS(Transactions!$G$6:$G$1000,Transactions!$C$6:$C$1000,$A9,Transactions!$F$6:$F$1000,"Supplier Return",Transactions!$A$6:$A$1000,">="&Settings!$B$5,Transactions!$A$6:$A$1000,"<="&Settings!$B$7) -> 1 | I9: =SUMIFS(Transactions!$G$6:$G$1000,Transactions!$C$6:$C$1000,$A9,Transactions!$F$6:$F$1000,"Damaged",Transactions!$A$6:$A$1000,">="&Settings!$B$5,Transactions!$A$6:$A$1000,"<="&Settings!$B$7) -> 0 | J9: =D9+E9+F9-G9-H9-I9 -> 27 | K9: 27 | L9: =IF(K9="","",K9-J9) -> 0 | M9: =Products!F9 -> 9800 | N9: =IF(L9="","",L9*M9) -> 0 | O9: =IF(OR(K9="",J9<=0),"",L9/J9) -> 0 | P9: =IF(K9="","Not counted",IF(L9=0,"Match",IF(L9<0,"Shortage","Overage"))) -> Match
A10: =Products!A10 -> NDL001 | B10: =Products!B10 -> Instant Noodles Chicken 70g | C10: =Products!D10 -> Mushin Noodles & Foods Ltd | D10: 118 | E10: =SUMIFS(Transactions!$G$6:$G$1000,Transactions!$C$6:$C$1000,$A10,Transactions!$F$6:$F$1000,"Purchase",Transactions!$A$6:$A$1000,">="&Settings!$B$5,Transactions!$A$6:$A$1000,"<="&Settings!$B$7) -> 80 | F10: =SUMIFS(Transactions!$G$6:$G$1000,Transactions!$C$6:$C$1000,$A10,Transactions!$F$6:$F$1000,"Sales Return",Transactions!$A$6:$A$1000,">="&Settings!$B$5,Transactions!$A$6:$A$1000,"<="&Settings!$B$7) -> 2 | G10: =SUMIFS(Transactions!$G$6:$G$1000,Transactions!$C$6:$C$1000,$A10,Transactions!$F$6:$F$1000,"Sale",Transactions!$A$6:$A$1000,">="&Settings!$B$5,Transactions!$A$6:$A$1000,"<="&Settings!$B$7) -> 90 | H10: =SUMIFS(Transactions!$G$6:$G$1000,Transactions!$C$6:$C$1000,$A10,Transactions!$F$6:$F$1000,"Supplier Return",Transactions!$A$6:$A$1000,">="&Settings!$B$5,Transactions!$A$6:$A$1000,"<="&Settings!$B$7) -> 0 | I10: =SUMIFS(Transactions!$G$6:$G$1000,Transactions!$C$6:$C$1000,$A10,Transactions!$F$6:$F$1000,"Damaged",Transactions!$A$6:$A$1000,">="&Settings!$B$5,Transactions!$A$6:$A$1000,"<="&Settings!$B$7) -> 2 | J10: =D10+E10+F10-G10-H10-I10 -> 108 | K10: 105 | L10: =IF(K10="","",K10-J10) -> -3 | M10: =Products!F10 -> 7600 | N10: =IF(L10="","",L10*M10) -> -22800 | O10: =IF(OR(K10="",J10<=0),"",L10/J10) -> -0.027777778 | P10: =IF(K10="","Not counted",IF(L10=0,"Match",IF(L10<0,"Shortage","Overage"))) -> Shortage
A11: =Products!A11 -> NDL002 | B11: =Products!B11 -> Instant Noodles Onion 70g | C11: =Products!D11 -> Mushin Noodles & Foods Ltd | D11: 27 | E11: =SUMIFS(Transactions!$G$6:$G$1000,Transactions!$C$6:$C$1000,$A11,Transactions!$F$6:$F$1000,"Purchase",Transactions!$A$6:$A$1000,">="&Settings!$B$5,Transactions!$A$6:$A$1000,"<="&Settings!$B$7) -> 29 | F11: =SUMIFS(Transactions!$G$6:$G$1000,Transactions!$C$6:$C$1000,$A11,Transactions!$F$6:$F$1000,"Sales Return",Transactions!$A$6:$A$1000,">="&Settings!$B$5,Transactions!$A$6:$A$1000,"<="&Settings!$B$7) -> 0 | G11: =SUMIFS(Transactions!$G$6:$G$1000,Transactions!$C$6:$C$1000,$A11,Transactions!$F$6:$F$1000,"Sale",Transactions!$A$6:$A$1000,">="&Settings!$B$5,Transactions!$A$6:$A$1000,"<="&Settings!$B$7) -> 54 | H11: =SUMIFS(Transactions!$G$6:$G$1000,Transactions!$C$6:$C$1000,$A11,Transactions!$F$6:$F$1000,"Supplier Return",Transactions!$A$6:$A$1000,">="&Settings!$B$5,Transactions!$A$6:$A$1000,"<="&Settings!$B$7) -> 2 | I11: =SUMIFS(Transactions!$G$6:$G$1000,Transactions!$C$6:$C$1000,$A11,Transactions!$F$6:$F$1000,"Damaged",Transactions!$A$6:$A$1000,">="&Settings!$B$5,Transactions!$A$6:$A$1000,"<="&Settings!$B$7) -> 0 | J11: =D11+E11+F11-G11-H11-I11 -> 0 | K11: 0 | L11: =IF(K11="","",K11-J11) -> 0 | M11: =Products!F11 -> 7700 | N11: =IF(L11="","",L11*M11) -> 0 | O11: =IF(OR(K11="",J11<=0),"",L11/J11) | P11: =IF(K11="","Not counted",IF(L11=0,"Match",IF(L11<0,"Shortage","Overage"))) -> Match
A12: =Products!A12 -> NDL003 | B12: =Products!B12 -> Spaghetti 500g | C12: =Products!D12 -> Mushin Noodles & Foods Ltd | D12: 35 | E12: =SUMIFS(Transactions!$G$6:$G$1000,Transactions!$C$6:$C$1000,$A12,Transactions!$F$6:$F$1000,"Purchase",Transactions!$A$6:$A$1000,">="&Settings!$B$5,Transactions!$A$6:$A$1000,"<="&Settings!$B$7) -> 0 | F12: =SUMIFS(Transactions!$G$6:$G$1000,Transactions!$C$6:$C$1000,$A12,Transactions!$F$6:$F$1000,"Sales Return",Transactions!$A$6:$A$1000,">="&Settings!$B$5,Transactions!$A$6:$A$1000,"<="&Settings!$B$7) -> 0 | G12: =SUMIFS(Transactions!$G$6:$G$1000,Transactions!$C$6:$C$1000,$A12,Transactions!$F$6:$F$1000,"Sale",Transactions!$A$6:$A$1000,">="&Settings!$B$5,Transactions!$A$6:$A$1000,"<="&Settings!$B$7) -> 12 | H12: =SUMIFS(Transactions!$G$6:$G$1000,Transactions!$C$6:$C$1000,$A12,Transactions!$F$6:$F$1000,"Supplier Return",Transactions!$A$6:$A$1000,">="&Settings!$B$5,Transactions!$A$6:$A$1000,"<="&Settings!$B$7) -> 0 | I12: =SUMIFS(Transactions!$G$6:$G$1000,Transactions!$C$6:$C$1000,$A12,Transactions!$F$6:$F$1000,"Damaged",Transactions!$A$6:$A$1000,">="&Settings!$B$5,Transactions!$A$6:$A$1000,"<="&Settings!$B$7) -> 0 | J12: =D12+E12+F12-G12-H12-I12 -> 23 | K12: 24 | L12: =IF(K12="","",K12-J12) -> 1 | M12: =Products!F12 -> 11500 | N12: =IF(L12="","",L12*M12) -> 11500 | O12: =IF(OR(K12="",J12<=0),"",L12/J12) -> 0.043478261 | P12: =IF(K12="","Not counted",IF(L12=0,"Match",IF(L12<0,"Shortage","Overage"))) -> Overage
A13: =Products!A13 -> OIL001 | B13: =Products!B13 -> Vegetable Oil 5L | C13: =Products!D13 -> Ikorodu Oil Mills (Agent) | D13: 23 | E13: =SUMIFS(Transactions!$G$6:$G$1000,Transactions!$C$6:$C$1000,$A13,Transactions!$F$6:$F$1000,"Purchase",Transactions!$A$6:$A$1000,">="&Settings!$B$5,Transactions!$A$6:$A$1000,"<="&Settings!$B$7) -> 22 | F13: =SUMIFS(Transactions!$G$6:$G$1000,Transactions!$C$6:$C$1000,$A13,Transactions!$F$6:$F$1000,"Sales Return",Transactions!$A$6:$A$1000,">="&Settings!$B$5,Transactions!$A$6:$A$1000,"<="&Settings!$B$7) -> 1 | G13: =SUMIFS(Transactions!$G$6:$G$1000,Transactions!$C$6:$C$1000,$A13,Transactions!$F$6:$F$1000,"Sale",Transactions!$A$6:$A$1000,">="&Settings!$B$5,Transactions!$A$6:$A$1000,"<="&Settings!$B$7) -> 24 | H13: =SUMIFS(Transactions!$G$6:$G$1000,Transactions!$C$6:$C$1000,$A13,Transactions!$F$6:$F$1000,"Supplier Return",Transactions!$A$6:$A$1000,">="&Settings!$B$5,Transactions!$A$6:$A$1000,"<="&Settings!$B$7) -> 0 | I13: =SUMIFS(Transactions!$G$6:$G$1000,Transactions!$C$6:$C$1000,$A13,Transactions!$F$6:$F$1000,"Damaged",Transactions!$A$6:$A$1000,">="&Settings!$B$5,Transactions!$A$6:$A$1000,"<="&Settings!$B$7) -> 0 | J13: =D13+E13+F13-G13-H13-I13 -> 22 | K13: 21 | L13: =IF(K13="","",K13-J13) -> -1 | M13: =Products!F13 -> 38000 | N13: =IF(L13="","",L13*M13) -> -38000 | O13: =IF(OR(K13="",J13<=0),"",L13/J13) -> -0.045454545 | P13: =IF(K13="","Not counted",IF(L13=0,"Match",IF(L13<0,"Shortage","Overage"))) -> Shortage
A14: =Products!A14 -> OIL002 | B14: =Products!B14 -> Vegetable Oil 1L | C14: =Products!D14 -> Ikorodu Oil Mills (Agent) | D14: 28 | E14: =SUMIFS(Transactions!$G$6:$G$1000,Transactions!$C$6:$C$1000,$A14,Transactions!$F$6:$F$1000,"Purchase",Transactions!$A$6:$A$1000,">="&Settings!$B$5,Transactions!$A$6:$A$1000,"<="&Settings!$B$7) -> 0 | F14: =SUMIFS(Transactions!$G$6:$G$1000,Transactions!$C$6:$C$1000,$A14,Transactions!$F$6:$F$1000,"Sales Return",Transactions!$A$6:$A$1000,">="&Settings!$B$5,Transactions!$A$6:$A$1000,"<="&Settings!$B$7) -> 0 | G14: =SUMIFS(Transactions!$G$6:$G$1000,Transactions!$C$6:$C$1000,$A14,Transactions!$F$6:$F$1000,"Sale",Transactions!$A$6:$A$1000,">="&Settings!$B$5,Transactions!$A$6:$A$1000,"<="&Settings!$B$7) -> 10 | H14: =SUMIFS(Transactions!$G$6:$G$1000,Transactions!$C$6:$C$1000,$A14,Transactions!$F$6:$F$1000,"Supplier Return",Transactions!$A$6:$A$1000,">="&Settings!$B$5,Transactions!$A$6:$A$1000,"<="&Settings!$B$7) -> 0 | I14: =SUMIFS(Transactions!$G$6:$G$1000,Transactions!$C$6:$C$1000,$A14,Transactions!$F$6:$F$1000,"Damaged",Transactions!$A$6:$A$1000,">="&Settings!$B$5,Transactions!$A$6:$A$1000,"<="&Settings!$B$7) -> 1 | J14: =D14+E14+F14-G14-H14-I14 -> 17 | K14: 17 | L14: =IF(K14="","",K14-J14) -> 0 | M14: =Products!F14 -> 36000 | N14: =IF(L14="","",L14*M14) -> 0 | O14: =IF(OR(K14="",J14<=0),"",L14/J14) -> 0 | P14: =IF(K14="","Not counted",IF(L14=0,"Match",IF(L14<0,"Shortage","Overage"))) -> Match
A15: =Products!A15 -> DET001 | B15: =Products!B15 -> Detergent Powder 900g | C15: =Products!D15 -> Oshodi Home Care Supplies | D15: 31 | E15: =SUMIFS(Transactions!$G$6:$G$1000,Transactions!$C$6:$C$1000,$A15,Transactions!$F$6:$F$1000,"Purchase",Transactions!$A$6:$A$1000,">="&Settings!$B$5,Transactions!$A$6:$A$1000,"<="&Settings!$B$7) -> 24 | F15: =SUMIFS(Transactions!$G$6:$G$1000,Transactions!$C$6:$C$1000,$A15,Transactions!$F$6:$F$1000,"Sales Return",Transactions!$A$6:$A$1000,">="&Settings!$B$5,Transactions!$A$6:$A$1000,"<="&Settings!$B$7) -> 1 | G15: =SUMIFS(Transactions!$G$6:$G$1000,Transactions!$C$6:$C$1000,$A15,Transactions!$F$6:$F$1000,"Sale",Transactions!$A$6:$A$1000,">="&Settings!$B$5,Transactions!$A$6:$A$1000,"<="&Settings!$B$7) -> 30 | H15: =SUMIFS(Transactions!$G$6:$G$1000,Transactions!$C$6:$C$1000,$A15,Transactions!$F$6:$F$1000,"Supplier Return",Transactions!$A$6:$A$1000,">="&Settings!$B$5,Transactions!$A$6:$A$1000,"<="&Settings!$B$7) -> 0 | I15: =SUMIFS(Transactions!$G$6:$G$1000,Transactions!$C$6:$C$1000,$A15,Transactions!$F$6:$F$1000,"Damaged",Transactions!$A$6:$A$1000,">="&Settings!$B$5,Transactions!$A$6:$A$1000,"<="&Settings!$B$7) -> 0 | J15: =D15+E15+F15-G15-H15-I15 -> 26 | K15: 27 | L15: =IF(K15="","",K15-J15) -> 1 | M15: =Products!F15 -> 14400 | N15: =IF(L15="","",L15*M15) -> 14400 | O15: =IF(OR(K15="",J15<=0),"",L15/J15) -> 0.038461538 | P15: =IF(K15="","Not counted",IF(L15=0,"Match",IF(L15<0,"Shortage","Overage"))) -> Overage
A16: =Products!A16 -> DET002 | B16: =Products!B16 -> Detergent Powder 400g | C16: =Products!D16 -> Oshodi Home Care Supplies | D16: 51 | E16: =SUMIFS(Transactions!$G$6:$G$1000,Transactions!$C$6:$C$1000,$A16,Transactions!$F$6:$F$1000,"Purchase",Transactions!$A$6:$A$1000,">="&Settings!$B$5,Transactions!$A$6:$A$1000,"<="&Settings!$B$7) -> 0 | F16: =SUMIFS(Transactions!$G$6:$G$1000,Transactions!$C$6:$C$1000,$A16,Transactions!$F$6:$F$1000,"Sales Return",Transactions!$A$6:$A$1000,">="&Settings!$B$5,Transactions!$A$6:$A$1000,"<="&Settings!$B$7) -> 0 | G16: =SUMIFS(Transactions!$G$6:$G$1000,Transactions!$C$6:$C$1000,$A16,Transactions!$F$6:$F$1000,"Sale",Transactions!$A$6:$A$1000,">="&Settings!$B$5,Transactions!$A$6:$A$1000,"<="&Settings!$B$7) -> 20 | H16: =SUMIFS(Transactions!$G$6:$G$1000,Transactions!$C$6:$C$1000,$A16,Transactions!$F$6:$F$1000,"Supplier Return",Transactions!$A$6:$A$1000,">="&Settings!$B$5,Transactions!$A$6:$A$1000,"<="&Settings!$B$7) -> 0 | I16: =SUMIFS(Transactions!$G$6:$G$1000,Transactions!$C$6:$C$1000,$A16,Transactions!$F$6:$F$1000,"Damaged",Transactions!$A$6:$A$1000,">="&Settings!$B$5,Transactions!$A$6:$A$1000,"<="&Settings!$B$7) -> 1 | J16: =D16+E16+F16-G16-H16-I16 -> 30 | K16: 30 | L16: =IF(K16="","",K16-J16) -> 0 | M16: =Products!F16 -> 17000 | N16: =IF(L16="","",L16*M16) -> 0 | O16: =IF(OR(K16="",J16<=0),"",L16/J16) -> 0 | P16: =IF(K16="","Not counted",IF(L16=0,"Match",IF(L16<0,"Shortage","Overage"))) -> Match
A17: =Products!A17 -> DET003 | B17: =Products!B17 -> Laundry Bar Soap | C17: =Products!D17 -> Oshodi Home Care Supplies | D17: 35 | E17: =SUMIFS(Transactions!$G$6:$G$1000,Transactions!$C$6:$C$1000,$A17,Transactions!$F$6:$F$1000,"Purchase",Transactions!$A$6:$A$1000,">="&Settings!$B$5,Transactions!$A$6:$A$1000,"<="&Settings!$B$7) -> 0 | F17: =SUMIFS(Transactions!$G$6:$G$1000,Transactions!$C$6:$C$1000,$A17,Transactions!$F$6:$F$1000,"Sales Return",Transactions!$A$6:$A$1000,">="&Settings!$B$5,Transactions!$A$6:$A$1000,"<="&Settings!$B$7) -> 0 | G17: =SUMIFS(Transactions!$G$6:$G$1000,Transactions!$C$6:$C$1000,$A17,Transactions!$F$6:$F$1000,"Sale",Transactions!$A$6:$A$1000,">="&Settings!$B$5,Transactions!$A$6:$A$1000,"<="&Settings!$B$7) -> 7 | H17: =SUMIFS(Transactions!$G$6:$G$1000,Transactions!$C$6:$C$1000,$A17,Transactions!$F$6:$F$1000,"Supplier Return",Transactions!$A$6:$A$1000,">="&Settings!$B$5,Transactions!$A$6:$A$1000,"<="&Settings!$B$7) -> 0 | I17: =SUMIFS(Transactions!$G$6:$G$1000,Transactions!$C$6:$C$1000,$A17,Transactions!$F$6:$F$1000,"Damaged",Transactions!$A$6:$A$1000,">="&Settings!$B$5,Transactions!$A$6:$A$1000,"<="&Settings!$B$7) -> 0 | J17: =D17+E17+F17-G17-H17-I17 -> 28 | K17: 28 | L17: =IF(K17="","",K17-J17) -> 0 | M17: =Products!F17 -> 9000 | N17: =IF(L17="","",L17*M17) -> 0 | O17: =IF(OR(K17="",J17<=0),"",L17/J17) -> 0 | P17: =IF(K17="","Not counted",IF(L17=0,"Match",IF(L17<0,"Shortage","Overage"))) -> Match
... A23: =Products!A23 -> FDS006 | B23: =Products!B23 -> Cocoa Beverage Powder 400g | C23: =Products!D23 -> Idumota Dry Goods Traders | D23: 32 | E23: =SUMIFS(Transactions!$G$6:$G$1000,Transactions!$C$6:$C$1000,$A23,Transactions!$F$6:$F$1000,"Purchase",Transactions!$A$6:$A$1000,">="&Settings!$B$5,Transactions!$A$6:$A$1000,"<="&Settings!$B$7) -> 0 | F23: =SUMIFS(Transactions!$G$6:$G$1000,Transactions!$C$6:$C$1000,$A23,Transactions!$F$6:$F$1000,"Sales Return",Transactions!$A$6:$A$1000,">="&Settings!$B$5,Transactions!$A$6:$A$1000,"<="&Settings!$B$7) -> 0 | G23: =SUMIFS(Transactions!$G$6:$G$1000,Transactions!$C$6:$C$1000,$A23,Transactions!$F$6:$F$1000,"Sale",Transactions!$A$6:$A$1000,">="&Settings!$B$5,Transactions!$A$6:$A$1000,"<="&Settings!$B$7) -> 6 | H23: =SUMIFS(Transactions!$G$6:$G$1000,Transactions!$C$6:$C$1000,$A23,Transactions!$F$6:$F$1000,"Supplier Return",Transactions!$A$6:$A$1000,">="&Settings!$B$5,Transactions!$A$6:$A$1000,"<="&Settings!$B$7) -> 0 | I23: =SUMIFS(Transactions!$G$6:$G$1000,Transactions!$C$6:$C$1000,$A23,Transactions!$F$6:$F$1000,"Damaged",Transactions!$A$6:$A$1000,">="&Settings!$B$5,Transactions!$A$6:$A$1000,"<="&Settings!$B$7) -> 0 | J23: =D23+E23+F23-G23-H23-I23 -> 26 | K23: 26 | L23: =IF(K23="","",K23-J23) -> 0 | M23: =Products!F23 -> 21000 | N23: =IF(L23="","",L23*M23) -> 0 | O23: =IF(OR(K23="",J23<=0),"",L23/J23) -> 0 | P23: =IF(K23="","Not counted",IF(L23=0,"Match",IF(L23<0,"Shortage","Overage"))) -> Match
A24: TOTAL | D24: =SUM(D6:D23) -> 784 | E24: =SUM(E6:E23) -> 345 | F24: =SUM(F6:F23) -> 10 | G24: =SUM(G6:G23) -> 532 | H24: =SUM(H6:H23) -> 4 | I24: =SUM(I6:I23) -> 9 | J24: =SUM(J6:J23) -> 594 | K24: =SUM(K6:K23) -> 584 | L24: =SUM(L6:L23) -> -10 | N24: =SUM(N6:N23) -> -86900

Sheet Reorder Dashboard
A1: Reorder Alert Dashboard
A2: Stock on hand uses the physical count where entered. Minimum = average daily sales × (lead time + safety days). Blue Override cells let you set your own minimum.
A4: STOCK-OUT | B4: REORDER NOW | C4: APPROACHING | D4: OK | E4: Est. reorder value (₦)
A5: =COUNTIF($K$9:$K$26,"STOCK-OUT") -> 1 | B5: =COUNTIF($K$9:$K$26,"REORDER NOW") -> 4 | C5: =COUNTIF($K$9:$K$26,"APPROACHING") -> 3 | D5: =COUNTIF($K$9:$K$26,"OK") -> 10 | E5: =SUM(N9:N26) -> 3977800
A8: Product Code | B8: Product Name | C8: Supplier | D8: Lead Time (days) | E8: Stock on Hand | F8: Avg Daily Sales | G8: Days of Cover | H8: Calculated Minimum | I8: Minimum Override | J8: Effective Minimum | K8: Alert | L8: Suggested Order Qty | M8: Unit Cost (₦) | N8: Est. Order Value (₦) | O8: Stock Level Bar
A9: =Products!A6 -> BEV001 | B9: =Products!B6 -> Cola Soft Drink 50cl PET | C9: =Products!D6 -> Apapa Beverages Depot | D9: =Products!H6 -> 2 | E9: =IF(Register!K6="",Register!J6,Register!K6) -> 25 | F9: =Register!G6/Settings!$B$6 -> 10 | G9: =IF(F9=0,"n/a",E9/F9) -> 2.5 | H9: =ROUNDUP(F9*(D9+Settings!$B$8),0) -> 40 | J9: =IF(I9="",H9,I9) -> 40 | K9: =IF(E9<=0,"STOCK-OUT",IF(E9<=J9,"REORDER NOW",IF(E9<=J9*(1+Settings!$B$10),"APPROACHING","OK"))) -> REORDER NOW | L9: =IF(OR(K9="STOCK-OUT",K9="REORDER NOW"),MAX(0,ROUNDUP(F9*Settings!$B$9-E9,0)),0) -> 115 | M9: =Products!F6 -> 5200 | N9: =L9*M9 -> 598000 | O9: =IF(K9="STOCK-OUT",REPT("█",3),IF(K9="REORDER NOW",REPT("█",6),IF(K9="APPROACHING",REPT("█",9),REPT("█",12)))) -> ██████
A10: =Products!A7 -> BEV002 | B10: =Products!B7 -> Orange Soft Drink 50cl PET | C10: =Products!D7 -> Apapa Beverages Depot | D10: =Products!H7 -> 2 | E10: =IF(Register!K7="",Register!J7,Register!K7) -> 25 | F10: =Register!G7/Settings!$B$6 -> 7 | G10: =IF(F10=0,"n/a",E10/F10) -> 3.5714286 | H10: =ROUNDUP(F10*(D10+Settings!$B$8),0) -> 28 | J10: =IF(I10="",H10,I10) -> 28 | K10: =IF(E10<=0,"STOCK-OUT",IF(E10<=J10,"REORDER NOW",IF(E10<=J10*(1+Settings!$B$10),"APPROACHING","OK"))) -> REORDER NOW | L10: =IF(OR(K10="STOCK-OUT",K10="REORDER NOW"),MAX(0,ROUNDUP(F10*Settings!$B$9-E10,0)),0) -> 73 | M10: =Products!F7 -> 5200 | N10: =L10*M10 -> 379600 | O10: =IF(K10="STOCK-OUT",REPT("█",3),IF(K10="REORDER NOW",REPT("█",6),IF(K10="APPROACHING",REPT("█",9),REPT("█",12)))) -> ██████
A11: =Products!A8 -> BEV003 | B11: =Products!B8 -> Table Water 75cl | C11: =Products!D8 -> Apapa Beverages Depot | D11: =Products!H8 -> 2 | E11: =IF(Register!K8="",Register!J8,Register!K8) -> 55 | F11: =Register!G8/Settings!$B$6 -> 12 | G11: =IF(F11=0,"n/a",E11/F11) -> 4.5833333 | H11: =ROUNDUP(F11*(D11+Settings!$B$8),0) -> 48 | J11: =IF(I11="",H11,I11) -> 48 | K11: =IF(E11<=0,"STOCK-OUT",IF(E11<=J11,"REORDER NOW",IF(E11<=J11*(1+Settings!$B$10),"APPROACHING","OK"))) -> APPROACHING | L11: =IF(OR(K11="STOCK-OUT",K11="REORDER NOW"),MAX(0,ROUNDUP(F11*Settings!$B$9-E11,0)),0) -> 0 | M11: =Products!F8 -> 1900 | N11: =L11*M11 -> 0 | O11: =IF(K11="STOCK-OUT",REPT("█",3),IF(K11="REORDER NOW",REPT("█",6),IF(K11="APPROACHING",REPT("█",9),REPT("█",12)))) -> █████████
A12: =Products!A9 -> BEV004 | B12: =Products!B9 -> Malt Drink 33cl Can | C12: =Products!D9 -> Apapa Beverages Depot | D12: =Products!H9 -> 2 | E12: =IF(Register!K9="",Register!J9,Register!K9) -> 27 | F12: =Register!G9/Settings!$B$6 -> 1.5 | G12: =IF(F12=0,"n/a",E12/F12) -> 18 | H12: =ROUNDUP(F12*(D12+Settings!$B$8),0) -> 6 | J12: =IF(I12="",H12,I12) -> 6 | K12: =IF(E12<=0,"STOCK-OUT",IF(E12<=J12,"REORDER NOW",IF(E12<=J12*(1+Settings!$B$10),"APPROACHING","OK"))) -> OK | L12: =IF(OR(K12="STOCK-OUT",K12="REORDER NOW"),MAX(0,ROUNDUP(F12*Settings!$B$9-E12,0)),0) -> 0 | M12: =Products!F9 -> 9800 | N12: =L12*M12 -> 0 | O12: =IF(K12="STOCK-OUT",REPT("█",3),IF(K12="REORDER NOW",REPT("█",6),IF(K12="APPROACHING",REPT("█",9),REPT("█",12)))) -> ████████████
A13: =Products!A10 -> NDL001 | B13: =Products!B10 -> Instant Noodles Chicken 70g | C13: =Products!D10 -> Mushin Noodles & Foods Ltd | D13: =Products!H10 -> 3 | E13: =IF(Register!K10="",Register!J10,Register!K10) -> 105 | F13: =Register!G10/Settings!$B$6 -> 15 | G13: =IF(F13=0,"n/a",E13/F13) -> 7 | H13: =ROUNDUP(F13*(D13+Settings!$B$8),0) -> 75 | J13: =IF(I13="",H13,I13) -> 75 | K13: =IF(E13<=0,"STOCK-OUT",IF(E13<=J13,"REORDER NOW",IF(E13<=J13*(1+Settings!$B$10),"APPROACHING","OK"))) -> OK | L13: =IF(OR(K13="STOCK-OUT",K13="REORDER NOW"),MAX(0,ROUNDUP(F13*Settings!$B$9-E13,0)),0) -> 0 | M13: =Products!F10 -> 7600 | N13: =L13*M13 -> 0 | O13: =IF(K13="STOCK-OUT",REPT("█",3),IF(K13="REORDER NOW",REPT("█",6),IF(K13="APPROACHING",REPT("█",9),REPT("█",12)))) -> ████████████
A14: =Products!A11 -> NDL002 | B14: =Products!B11 -> Instant Noodles Onion 70g | C14: =Products!D11 -> Mushin Noodles & Foods Ltd | D14: =Products!H11 -> 3 | E14: =IF(Register!K11="",Register!J11,Register!K11) -> 0 | F14: =Register!G11/Settings!$B$6 -> 9 | G14: =IF(F14=0,"n/a",E14/F14) -> 0 | H14: =ROUNDUP(F14*(D14+Settings!$B$8),0) -> 45 | J14: =IF(I14="",H14,I14) -> 45 | K14: =IF(E14<=0,"STOCK-OUT",IF(E14<=J14,"REORDER NOW",IF(E14<=J14*(1+Settings!$B$10),"APPROACHING","OK"))) -> STOCK-OUT | L14: =IF(OR(K14="STOCK-OUT",K14="REORDER NOW"),MAX(0,ROUNDUP(F14*Settings!$B$9-E14,0)),0) -> 126 | M14: =Products!F11 -> 7700 | N14: =L14*M14 -> 970200 | O14: =IF(K14="STOCK-OUT",REPT("█",3),IF(K14="REORDER NOW",REPT("█",6),IF(K14="APPROACHING",REPT("█",9),REPT("█",12)))) -> ███
A15: =Products!A12 -> NDL003 | B15: =Products!B12 -> Spaghetti 500g | C15: =Products!D12 -> Mushin Noodles & Foods Ltd | D15: =Products!H12 -> 3 | E15: =IF(Register!K12="",Register!J12,Register!K12) -> 24 | F15: =Register!G12/Settings!$B$6 -> 2 | G15: =IF(F15=0,"n/a",E15/F15) -> 12 | H15: =ROUNDUP(F15*(D15+Settings!$B$8),0) -> 10 | J15: =IF(I15="",H15,I15) -> 10 | K15: =IF(E15<=0,"STOCK-OUT",IF(E15<=J15,"REORDER NOW",IF(E15<=J15*(1+Settings!$B$10),"APPROACHING","OK"))) -> OK | L15: =IF(OR(K15="STOCK-OUT",K15="REORDER NOW"),MAX(0,ROUNDUP(F15*Settings!$B$9-E15,0)),0) -> 0 | M15: =Products!F12 -> 11500 | N15: =L15*M15 -> 0 | O15: =IF(K15="STOCK-OUT",REPT("█",3),IF(K15="REORDER NOW",REPT("█",6),IF(K15="APPROACHING",REPT("█",9),REPT("█",12)))) -> ████████████
A16: =Products!A13 -> OIL001 | B16: =Products!B13 -> Vegetable Oil 5L | C16: =Products!D13 -> Ikorodu Oil Mills (Agent) | D16: =Products!H13 -> 4 | E16: =IF(Register!K13="",Register!J13,Register!K13) -> 21 | F16: =Register!G13/Settings!$B$6 -> 4 | G16: =IF(F16=0,"n/a",E16/F16) -> 5.25 | H16: =ROUNDUP(F16*(D16+Settings!$B$8),0) -> 24 | J16: =IF(I16="",H16,I16) -> 24 | K16: =IF(E16<=0,"STOCK-OUT",IF(E16<=J16,"REORDER NOW",IF(E16<=J16*(1+Settings!$B$10),"APPROACHING","OK"))) -> REORDER NOW | L16: =IF(OR(K16="STOCK-OUT",K16="REORDER NOW"),MAX(0,ROUNDUP(F16*Settings!$B$9-E16,0)),0) -> 35 | M16: =Products!F13 -> 38000 | N16: =L16*M16 -> 1330000 | O16: =IF(K16="STOCK-OUT",REPT("█",3),IF(K16="REORDER NOW",REPT("█",6),IF(K16="APPROACHING",REPT("█",9),REPT("█",12)))) -> ██████
A17: =Products!A14 -> OIL002 | B17: =Products!B14 -> Vegetable Oil 1L | C17: =Products!D14 -> Ikorodu Oil Mills (Agent) | D17: =Products!H14 -> 4 | E17: =IF(Register!K14="",Register!J14,Register!K14) -> 17 | F17: =Register!G14/Settings!$B$6 -> 1.6666667 | G17: =IF(F17=0,"n/a",E17/F17) -> 10.2 | H17: =ROUNDUP(F17*(D17+Settings!$B$8),0) -> 10 | J17: =IF(I17="",H17,I17) -> 10 | K17: =IF(E17<=0,"STOCK-OUT",IF(E17<=J17,"REORDER NOW",IF(E17<=J17*(1+Settings!$B$10),"APPROACHING","OK"))) -> OK | L17: =IF(OR(K17="STOCK-OUT",K17="REORDER NOW"),MAX(0,ROUNDUP(F17*Settings!$B$9-E17,0)),0) -> 0 | M17: =Products!F14 -> 36000 | N17: =L17*M17 -> 0 | O17: =IF(K17="STOCK-OUT",REPT("█",3),IF(K17="REORDER NOW",REPT("█",6),IF(K17="APPROACHING",REPT("█",9),REPT("█",12)))) -> ████████████
A18: =Products!A15 -> DET001 | B18: =Products!B15 -> Detergent Powder 900g | C18: =Products!D15 -> Oshodi Home Care Supplies | D18: =Products!H15 -> 3 | E18: =IF(Register!K15="",Register!J15,Register!K15) -> 27 | F18: =Register!G15/Settings!$B$6 -> 5 | G18: =IF(F18=0,"n/a",E18/F18) -> 5.4 | H18: =ROUNDUP(F18*(D18+Settings!$B$8),0) -> 25 | J18: =IF(I18="",H18,I18) -> 25 | K18: =IF(E18<=0,"STOCK-OUT",IF(E18<=J18,"REORDER NOW",IF(E18<=J18*(1+Settings!$B$10),"APPROACHING","OK"))) -> APPROACHING | L18: =IF(OR(K18="STOCK-OUT",K18="REORDER NOW"),MAX(0,ROUNDUP(F18*Settings!$B$9-E18,0)),0) -> 0 | M18: =Products!F15 -> 14400 | N18: =L18*M18 -> 0 | O18: =IF(K18="STOCK-OUT",REPT("█",3),IF(K18="REORDER NOW",REPT("█",6),IF(K18="APPROACHING",REPT("█",9),REPT("█",12)))) -> █████████
A19: =Products!A16 -> DET002 | B19: =Products!B16 -> Detergent Powder 400g | C19: =Products!D16 -> Oshodi Home Care Supplies | D19: =Products!H16 -> 3 | E19: =IF(Register!K16="",Register!J16,Register!K16) -> 30 | F19: =Register!G16/Settings!$B$6 -> 3.3333333 | G19: =IF(F19=0,"n/a",E19/F19) -> 9 | H19: =ROUNDUP(F19*(D19+Settings!$B$8),0) -> 17 | J19: =IF(I19="",H19,I19) -> 17 | K19: =IF(E19<=0,"STOCK-OUT",IF(E19<=J19,"REORDER NOW",IF(E19<=J19*(1+Settings!$B$10),"APPROACHING","OK"))) -> OK | L19: =IF(OR(K19="STOCK-OUT",K19="REORDER NOW"),MAX(0,ROUNDUP(F19*Settings!$B$9-E19,0)),0) -> 0 | M19: =Products!F16 -> 17000 | N19: =L19*M19 -> 0 | O19: =IF(K19="STOCK-OUT",REPT("█",3),IF(K19="REORDER NOW",REPT("█",6),IF(K19="APPROACHING",REPT("█",9),REPT("█",12)))) -> ████████████
A20: =Products!A17 -> DET003 | B20: =Products!B17 -> Laundry Bar Soap | C20: =Products!D17 -> Oshodi Home Care Supplies | D20: =Products!H17 -> 3 | E20: =IF(Register!K17="",Register!J17,Register!K17) -> 28 | F20: =Register!G17/Settings!$B$6 -> 1.1666667 | G20: =IF(F20=0,"n/a",E20/F20) -> 24 | H20: =ROUNDUP(F20*(D20+Settings!$B$8),0) -> 6 | J20: =IF(I20="",H20,I20) -> 6 | K20: =IF(E20<=0,"STOCK-OUT",IF(E20<=J20,"REORDER NOW",IF(E20<=J20*(1+Settings!$B$10),"APPROACHING","OK"))) -> OK | L20: =IF(OR(K20="STOCK-OUT",K20="REORDER NOW"),MAX(0,ROUNDUP(F20*Settings!$B$9-E20,0)),0) -> 0 | M20: =Products!F17 -> 9000 | N20: =L20*M20 -> 0 | O20: =IF(K20="STOCK-OUT",REPT("█",3),IF(K20="REORDER NOW",REPT("█",6),IF(K20="APPROACHING",REPT("█",9),REPT("█",12)))) -> ████████████
... A26: =Products!A23 -> FDS006 | B26: =Products!B23 -> Cocoa Beverage Powder 400g | C26: =Products!D23 -> Idumota Dry Goods Traders | D26: =Products!H23 -> 5 | E26: =IF(Register!K23="",Register!J23,Register!K23) -> 26 | F26: =Register!G23/Settings!$B$6 -> 1 | G26: =IF(F26=0,"n/a",E26/F26) -> 26 | H26: =ROUNDUP(F26*(D26+Settings!$B$8),0) -> 7 | J26: =IF(I26="",H26,I26) -> 7 | K26: =IF(E26<=0,"STOCK-OUT",IF(E26<=J26,"REORDER NOW",IF(E26<=J26*(1+Settings!$B$10),"APPROACHING","OK"))) -> OK | L26: =IF(OR(K26="STOCK-OUT",K26="REORDER NOW"),MAX(0,ROUNDUP(F26*Settings!$B$9-E26,0)),0) -> 0 | M26: =Products!F23 -> 21000 | N26: =L26*M26 -> 0 | O26: =IF(K26="STOCK-OUT",REPT("█",3),IF(K26="REORDER NOW",REPT("█",6),IF(K26="APPROACHING",REPT("█",9),REPT("█",12)))) -> ████████████
A29: Supplier order summary (SKUs flagged STOCK-OUT or REORDER NOW)
A30: Supplier | C30: SKUs to Order | D30: Order Value (₦) | E30: Lead Time (days)
A31: Apapa Beverages Depot | C31: =COUNTIFS($C$9:$C$26,$A31,$L$9:$L$26,">0") -> 2 | D31: =SUMIFS($N$9:$N$26,$C$9:$C$26,$A31) -> 977600 | E31: =IFERROR(INDEX(Products!$H$6:$H$60,MATCH($A31,Products!$D$6:$D$60,0)),"") -> 2
A32: Mushin Noodles & Foods Ltd | C32: =COUNTIFS($C$9:$C$26,$A32,$L$9:$L$26,">0") -> 1 | D32: =SUMIFS($N$9:$N$26,$C$9:$C$26,$A32) -> 970200 | E32: =IFERROR(INDEX(Products!$H$6:$H$60,MATCH($A32,Products!$D$6:$D$60,0)),"") -> 3
A33: Ikorodu Oil Mills (Agent) | C33: =COUNTIFS($C$9:$C$26,$A33,$L$9:$L$26,">0") -> 1 | D33: =SUMIFS($N$9:$N$26,$C$9:$C$26,$A33) -> 1330000 | E33: =IFERROR(INDEX(Products!$H$6:$H$60,MATCH($A33,Products!$D$6:$D$60,0)),"") -> 4
A34: Oshodi Home Care Supplies | C34: =COUNTIFS($C$9:$C$26,$A34,$L$9:$L$26,">0") -> 0 | D34: =SUMIFS($N$9:$N$26,$C$9:$C$26,$A34) -> 0 | E34: =IFERROR(INDEX(Products!$H$6:$H$60,MATCH($A34,Products!$D$6:$D$60,0)),"") -> 3
A35: Idumota Dry Goods Traders | C35: =COUNTIFS($C$9:$C$26,$A35,$L$9:$L$26,">0") -> 1 | D35: =SUMIFS($N$9:$N$26,$C$9:$C$26,$A35) -> 700000 | E35: =IFERROR(INDEX(Products!$H$6:$H$60,MATCH($A35,Products!$D$6:$D$60,0)),"") -> 5
A36: TOTAL | C36: =SUM(C31:C35) -> 5 | D36: =SUM(D31:D35) -> 3977800

Sheet Reconciliation
A1: Stock Reconciliation Report
A2: Book balance (from the Register) compared with the physical count. Variance = Physical − Book. Shortages are negative.
A3: ="Week: "&TEXT(Settings!B5,"dd mmm yyyy")&" to "&TEXT(Settings!B7,"dd mmm yyyy") -> Week: 19 Oct 2026 to 24 Oct 2026
A4: SKUs counted | B4: =COUNT(D15:D32) -> 18 | C4: Shortage value (₦ at cost) | E4: =SUMIF(G15:G32,"<0") -> -112800
A5: SKUs matching | B5: =COUNTIF(I15:I32,"Match") -> 11 | C5: Overage value (₦ at cost) | E5: =SUMIF(G15:G32,">0") -> 25900
A6: SKUs with shortage | B6: =COUNTIF(I15:I32,"Shortage") -> 5 | C6: Net variance (₦ at cost) | E6: =SUM(G15:G32) -> -86900
A7: SKUs with overage | B7: =COUNTIF(I15:I32,"Overage") -> 2 | C7: Damaged stock (₦ at cost) | E7: =SUMPRODUCT(Register!I6:I23,Register!M6:M23) -> 123300
A8: Stock record accuracy (% SKUs matching) | B8: =IFERROR(B5/B4,0) -> 0.61111111 | C8: Potential loss: shortages + damaged (₦) | E8: =-E4+E7 -> 236100
A9: HIGH-priority variances | B9: =COUNTIF(J15:J32,"HIGH") -> 5 | C9: Potential loss as % of net sales | E9: =IFERROR(E8/'Weekly Report'!B11,0) -> 0.036605786
A14: Product Code | B14: Product Name | C14: Book Balance | D14: Physical Count | E14: Variance (units) | F14: Unit Cost (₦) | G14: Variance Value (₦) | H14: Variance % | I14: Result | J14: Priority | K14: Investigation Note (sample)
A15: =Register!A6 -> BEV001 | B15: =Register!B6 -> Cola Soft Drink 50cl PET | C15: =Register!J6 -> 27 | D15: =IF(Register!K6="","",Register!K6) -> 25 | E15: =Register!L6 -> -2 | F15: =Register!M6 -> 5200 | G15: =Register!N6 -> -10400 | H15: =Register!O6 -> -0.074074074 | I15: =Register!P6 -> Shortage | J15: =IF(OR(I15="Match",I15="Not counted"),"-",IF(OR(ABS(G15)>=Settings!$B$12,IF(H15="",0,ABS(H15))>=Settings!$B$11),"HIGH","LOW")) -> HIGH | K15: Suspected unrecorded cash sale on Saturday; check van loading sheet.
A16: =Register!A7 -> BEV002 | B16: =Register!B7 -> Orange Soft Drink 50cl PET | C16: =Register!J7 -> 25 | D16: =IF(Register!K7="","",Register!K7) -> 25 | E16: =Register!L7 -> 0 | F16: =Register!M7 -> 5200 | G16: =Register!N7 -> 0 | H16: =Register!O7 -> 0 | I16: =Register!P7 -> Match | J16: =IF(OR(I16="Match",I16="Not counted"),"-",IF(OR(ABS(G16)>=Settings!$B$12,IF(H16="",0,ABS(H16))>=Settings!$B$11),"HIGH","LOW")) -> -
A17: =Register!A8 -> BEV003 | B17: =Register!B8 -> Table Water 75cl | C17: =Register!J8 -> 59 | D17: =IF(Register!K8="","",Register!K8) -> 55 | E17: =Register!L8 -> -4 | F17: =Register!M8 -> 1900 | G17: =Register!N8 -> -7600 | H17: =Register!O8 -> -0.06779661 | I17: =Register!P8 -> Shortage | J17: =IF(OR(I17="Match",I17="Not counted"),"-",IF(OR(ABS(G17)>=Settings!$B$12,IF(H17="",0,ABS(H17))>=Settings!$B$11),"HIGH","LOW")) -> HIGH | K17: Pack damage may not have been logged at offloading; confirm with storekeeper.
A18: =Register!A9 -> BEV004 | B18: =Register!B9 -> Malt Drink 33cl Can | C18: =Register!J9 -> 27 | D18: =IF(Register!K9="","",Register!K9) -> 27 | E18: =Register!L9 -> 0 | F18: =Register!M9 -> 9800 | G18: =Register!N9 -> 0 | H18: =Register!O9 -> 0 | I18: =Register!P9 -> Match | J18: =IF(OR(I18="Match",I18="Not counted"),"-",IF(OR(ABS(G18)>=Settings!$B$12,IF(H18="",0,ABS(H18))>=Settings!$B$11),"HIGH","LOW")) -> -
A19: =Register!A10 -> NDL001 | B19: =Register!B10 -> Instant Noodles Chicken 70g | C19: =Register!J10 -> 108 | D19: =IF(Register!K10="","",Register!K10) -> 105 | E19: =Register!L10 -> -3 | F19: =Register!M10 -> 7600 | G19: =Register!N10 -> -22800 | H19: =Register!O10 -> -0.027777778 | I19: =Register!P10 -> Shortage | J19: =IF(OR(I19="Match",I19="Not counted"),"-",IF(OR(ABS(G19)>=Settings!$B$12,IF(H19="",0,ABS(H19))>=Settings!$B$11),"HIGH","LOW")) -> HIGH | K19: Possible bonus cartons given to customers without paperwork.
A20: =Register!A11 -> NDL002 | B20: =Register!B11 -> Instant Noodles Onion 70g | C20: =Register!J11 -> 0 | D20: =IF(Register!K11="","",Register!K11) -> 0 | E20: =Register!L11 -> 0 | F20: =Register!M11 -> 7700 | G20: =Register!N11 -> 0 | H20: =Register!O11 | I20: =Register!P11 -> Match | J20: =IF(OR(I20="Match",I20="Not counted"),"-",IF(OR(ABS(G20)>=Settings!$B$12,IF(H20="",0,ABS(H20))>=Settings!$B$11),"HIGH","LOW")) -> -
A21: =Register!A12 -> NDL003 | B21: =Register!B12 -> Spaghetti 500g | C21: =Register!J12 -> 23 | D21: =IF(Register!K12="","",Register!K12) -> 24 | E21: =Register!L12 -> 1 | F21: =Register!M12 -> 11500 | G21: =Register!N12 -> 11500 | H21: =Register!O12 -> 0.043478261 | I21: =Register!P12 -> Overage | J21: =IF(OR(I21="Match",I21="Not counted"),"-",IF(OR(ABS(G21)>=Settings!$B$12,IF(H21="",0,ABS(H21))>=Settings!$B$11),"HIGH","LOW")) -> LOW | K21: Overage: supplier delivery may include extra cartons; verify delivery note.
A22: =Register!A13 -> OIL001 | B22: =Register!B13 -> Vegetable Oil 5L | C22: =Register!J13 -> 22 | D22: =IF(Register!K13="","",Register!K13) -> 21 | E22: =Register!L13 -> -1 | F22: =Register!M13 -> 38000 | G22: =Register!N13 -> -38000 | H22: =Register!O13 -> -0.045454545 | I22: =Register!P13 -> Shortage | J22: =IF(OR(I22="Match",I22="Not counted"),"-",IF(OR(ABS(G22)>=Settings!$B$12,IF(H22="",0,ABS(H22))>=Settings!$B$11),"HIGH","LOW")) -> HIGH | K22: Inspect 5L stack for leakage or pilferage; recount.
A23: =Register!A14 -> OIL002 | B23: =Register!B14 -> Vegetable Oil 1L | C23: =Register!J14 -> 17 | D23: =IF(Register!K14="","",Register!K14) -> 17 | E23: =Register!L14 -> 0 | F23: =Register!M14 -> 36000 | G23: =Register!N14 -> 0 | H23: =Register!O14 -> 0 | I23: =Register!P14 -> Match | J23: =IF(OR(I23="Match",I23="Not counted"),"-",IF(OR(ABS(G23)>=Settings!$B$12,IF(H23="",0,ABS(H23))>=Settings!$B$11),"HIGH","LOW")) -> -
A24: =Register!A15 -> DET001 | B24: =Register!B15 -> Detergent Powder 900g | C24: =Register!J15 -> 26 | D24: =IF(Register!K15="","",Register!K15) -> 27 | E24: =Register!L15 -> 1 | F24: =Register!M15 -> 14400 | G24: =Register!N15 -> 14400 | H24: =Register!O15 -> 0.038461538 | I24: =Register!P15 -> Overage | J24: =IF(OR(I24="Match",I24="Not counted"),"-",IF(OR(ABS(G24)>=Settings!$B$12,IF(H24="",0,ABS(H24))>=Settings!$B$11),"HIGH","LOW")) -> LOW | K24: Overage: possible unrecorded customer return.
A25: =Register!A16 -> DET002 | B25: =Register!B16 -> Detergent Powder 400g | C25: =Register!J16 -> 30 | D25: =IF(Register!K16="","",Register!K16) -> 30 | E25: =Register!L16 -> 0 | F25: =Register!M16 -> 17000 | G25: =Register!N16 -> 0 | H25: =Register!O16 -> 0 | I25: =Register!P16 -> Match | J25: =IF(OR(I25="Match",I25="Not counted"),"-",IF(OR(ABS(G25)>=Settings!$B$12,IF(H25="",0,ABS(H25))>=Settings!$B$11),"HIGH","LOW")) -> -
A26: =Register!A17 -> DET003 | B26: =Register!B17 -> Laundry Bar Soap | C26: =Register!J17 -> 28 | D26: =IF(Register!K17="","",Register!K17) -> 28 | E26: =Register!L17 -> 0 | F26: =Register!M17 -> 9000 | G26: =Register!N17 -> 0 | H26: =Register!O17 -> 0 | I26: =Register!P17 -> Match | J26: =IF(OR(I26="Match",I26="Not counted"),"-",IF(OR(ABS(G26)>=Settings!$B$12,IF(H26="",0,ABS(H26))>=Settings!$B$11),"HIGH","LOW")) -> -
A27: =Register!A18 -> FDS001 | B27: =Register!B18 -> Evaporated Milk 160g Tin | C27: =Register!J18 -> 17 | D27: =IF(Register!K18="","",Register!K18) -> 17 | E27: =Register!L18 -> 0 | F27: =Register!M18 -> 28000 | G27: =Register!N18 -> 0 | H27: =Register!O18 -> 0 | I27: =Register!P18 -> Match | J27: =IF(OR(I27="Match",I27="Not counted"),"-",IF(OR(ABS(G27)>=Settings!$B$12,IF(H27="",0,ABS(H27))>=Settings!$B$11),"HIGH","LOW")) -> -
A28: =Register!A19 -> FDS002 | B28: =Register!B19 -> Tomato Paste 70g Sachet | C28: =Register!J19 -> 36 | D28: =IF(Register!K19="","",Register!K19) -> 36 | E28: =Register!L19 -> 0 | F28: =Register!M19 -> 15500 | G28: =Register!N19 -> 0 | H28: =Register!O19 -> 0 | I28: =Register!P19 -> Match | J28: =IF(OR(I28="Match",I28="Not counted"),"-",IF(OR(ABS(G28)>=Settings!$B$12,IF(H28="",0,ABS(H28))>=Settings!$B$11),"HIGH","LOW")) -> -
A29: =Register!A20 -> FDS003 | B29: =Register!B20 -> Seasoning Cubes | C29: =Register!J20 -> 35 | D29: =IF(Register!K20="","",Register!K20) -> 35 | E29: =Register!L20 -> 0 | F29: =Register!M20 -> 14000 | G29: =Register!N20 -> 0 | H29: =Register!O20 -> 0 | I29: =Register!P20 -> Match | J29: =IF(OR(I29="Match",I29="Not counted"),"-",IF(OR(ABS(G29)>=Settings!$B$12,IF(H29="",0,ABS(H29))>=Settings!$B$11),"HIGH","LOW")) -> -
A30: =Register!A21 -> FDS004 | B30: =Register!B21 -> Granulated Sugar 500g | C30: =Register!J21 -> 68 | D30: =IF(Register!K21="","",Register!K21) -> 66 | E30: =Register!L21 -> -2 | F30: =Register!M21 -> 17000 | G30: =Register!N21 -> -34000 | H30: =Register!O21 -> -0.029411765 | I30: =Register!P21 -> Shortage | J30: =IF(OR(I30="Match",I30="Not counted"),"-",IF(OR(ABS(G30)>=Settings!$B$12,IF(H30="",0,ABS(H30))>=Settings!$B$11),"HIGH","LOW")) -> HIGH | K30: Suspected counting error; recount before adjusting book.
A31: =Register!A22 -> FDS005 | B31: =Register!B22 -> Table Salt 500g | C31: =Register!J22 -> 20 | D31: =IF(Register!K22="","",Register!K22) -> 20 | E31: =Register!L22 -> 0 | F31: =Register!M22 -> 6500 | G31: =Register!N22 -> 0 | H31: =Register!O22 -> 0 | I31: =Register!P22 -> Match | J31: =IF(OR(I31="Match",I31="Not counted"),"-",IF(OR(ABS(G31)>=Settings!$B$12,IF(H31="",0,ABS(H31))>=Settings!$B$11),"HIGH","LOW")) -> -
A32: =Register!A23 -> FDS006 | B32: =Register!B23 -> Cocoa Beverage Powder 400g | C32: =Register!J23 -> 26 | D32: =IF(Register!K23="","",Register!K23) -> 26 | E32: =Register!L23 -> 0 | F32: =Register!M23 -> 21000 | G32: =Register!N23 -> 0 | H32: =Register!O23 -> 0 | I32: =Register!P23 -> Match | J32: =IF(OR(I32="Match",I32="Not counted"),"-",IF(OR(ABS(G32)>=Settings!$B$12,IF(H32="",0,ABS(H32))>=Settings!$B$11),"HIGH","LOW")) -> -
A33: TOTAL | C33: =SUM(C15:C32) -> 594 | D33: =SUM(D15:D32) -> 584 | E33: =SUM(E15:E32) -> -10 | G33: =SUM(G15:G32) -> -86900

Sheet Movers Analysis
A1: Fast-Moving and Slow-Moving Product Analysis
A2: Ranked by units sold. Row order reflects the sample week; use the Rank column if data changes. Thresholds are on Settings.
A3: ="Fast-moving: weekly turnover ≥ "&TEXT(Settings!B13,"0.00")&" | Slow-moving: weekly turnover < "&TEXT(Settings!B14,"0.00")&" | Medium: in between" -> Fast-moving: weekly turnover ≥ 1.00 | Slow-moving: weekly turnover < 0.50 | Medium: in between
A5: Sales Rank | B5: Product Code | C5: Product Name | D5: Units Sold | E5: Share of Units Sold | F5: Sales Value (₦) | G5: Average Stock | H5: Weekly Turnover (x) | I5: Annualised Turns (x) | J5: Days of Stock on Hand | K5: Classification | L5: Turnover Rank (1 = slowest)
A6: =RANK(D6,$D$6:$D$23,0)+COUNTIF($D$6:D6,D6)-1 -> 1 | B6: NDL001 | C6: =INDEX(Register!$B$6:$B$23,MATCH(B6,Register!$A$6:$A$23,0)) -> Instant Noodles Chicken 70g | D6: =INDEX(Register!$G$6:$G$23,MATCH(B6,Register!$A$6:$A$23,0)) -> 90 | E6: =IFERROR(D6/SUM($D$6:$D$23),0) -> 0.16917293 | F6: =SUMIFS(Transactions!$K$6:$K$1000,Transactions!$C$6:$C$1000,B6,Transactions!$F$6:$F$1000,"Sale",Transactions!$A$6:$A$1000,">="&Settings!$B$5,Transactions!$A$6:$A$1000,"<="&Settings!$B$7) -> 756000 | G6: =(INDEX(Register!$D$6:$D$23,MATCH(B6,Register!$A$6:$A$23,0))+INDEX('Reorder Dashboard'!$E$9:$E$26,MATCH(B6,'Reorder Dashboard'!$A$9:$A$26,0)))/2 -> 111.5 | H6: =IF(G6=0,0,D6/G6) -> 0.80717489 | I6: =H6*52 -> 41.973094 | J6: =IF(D6=0,"n/a",G6/(D6/Settings!$B$6)) -> 7.4333333 | K6: =IF(H6>=Settings!$B$13,"Fast-moving",IF(H6<Settings!$B$14,"Slow-moving","Medium")) -> Medium | L6: =RANK(H6,$H$6:$H$23,1)+COUNTIF($H$6:H6,H6)-1 -> 11
A7: =RANK(D7,$D$6:$D$23,0)+COUNTIF($D$6:D7,D7)-1 -> 2 | B7: BEV003 | C7: =INDEX(Register!$B$6:$B$23,MATCH(B7,Register!$A$6:$A$23,0)) -> Table Water 75cl | D7: =INDEX(Register!$G$6:$G$23,MATCH(B7,Register!$A$6:$A$23,0)) -> 72 | E7: =IFERROR(D7/SUM($D$6:$D$23),0) -> 0.13533835 | F7: =SUMIFS(Transactions!$K$6:$K$1000,Transactions!$C$6:$C$1000,B7,Transactions!$F$6:$F$1000,"Sale",Transactions!$A$6:$A$1000,">="&Settings!$B$5,Transactions!$A$6:$A$1000,"<="&Settings!$B$7) -> 165600 | G7: =(INDEX(Register!$D$6:$D$23,MATCH(B7,Register!$A$6:$A$23,0))+INDEX('Reorder Dashboard'!$E$9:$E$26,MATCH(B7,'Reorder Dashboard'!$A$9:$A$26,0)))/2 -> 59.5 | H7: =IF(G7=0,0,D7/G7) -> 1.210084 | I7: =H7*52 -> 62.92437 | J7: =IF(D7=0,"n/a",G7/(D7/Settings!$B$6)) -> 4.9583333 | K7: =IF(H7>=Settings!$B$13,"Fast-moving",IF(H7<Settings!$B$14,"Slow-moving","Medium")) -> Fast-moving | L7: =RANK(H7,$H$6:$H$23,1)+COUNTIF($H$6:H7,H7)-1 -> 15
A8: =RANK(D8,$D$6:$D$23,0)+COUNTIF($D$6:D8,D8)-1 -> 3 | B8: BEV001 | C8: =INDEX(Register!$B$6:$B$23,MATCH(B8,Register!$A$6:$A$23,0)) -> Cola Soft Drink 50cl PET | D8: =INDEX(Register!$G$6:$G$23,MATCH(B8,Register!$A$6:$A$23,0)) -> 60 | E8: =IFERROR(D8/SUM($D$6:$D$23),0) -> 0.11278195 | F8: =SUMIFS(Transactions!$K$6:$K$1000,Transactions!$C$6:$C$1000,B8,Transactions!$F$6:$F$1000,"Sale",Transactions!$A$6:$A$1000,">="&Settings!$B$5,Transactions!$A$6:$A$1000,"<="&Settings!$B$7) -> 354000 | G8: =(INDEX(Register!$D$6:$D$23,MATCH(B8,Register!$A$6:$A$23,0))+INDEX('Reorder Dashboard'!$E$9:$E$26,MATCH(B8,'Reorder Dashboard'!$A$9:$A$26,0)))/2 -> 28 | H8: =IF(G8=0,0,D8/G8) -> 2.1428571 | I8: =H8*52 -> 111.42857 | J8: =IF(D8=0,"n/a",G8/(D8/Settings!$B$6)) -> 2.8 | K8: =IF(H8>=Settings!$B$13,"Fast-moving",IF(H8<Settings!$B$14,"Slow-moving","Medium")) -> Fast-moving | L8: =RANK(H8,$H$6:$H$23,1)+COUNTIF($H$6:H8,H8)-1 -> 17
A9: =RANK(D9,$D$6:$D$23,0)+COUNTIF($D$6:D9,D9)-1 -> 4 | B9: NDL002 | C9: =INDEX(Register!$B$6:$B$23,MATCH(B9,Register!$A$6:$A$23,0)) -> Instant Noodles Onion 70g | D9: =INDEX(Register!$G$6:$G$23,MATCH(B9,Register!$A$6:$A$23,0)) -> 54 | E9: =IFERROR(D9/SUM($D$6:$D$23),0) -> 0.10150376 | F9: =SUMIFS(Transactions!$K$6:$K$1000,Transactions!$C$6:$C$1000,B9,Transactions!$F$6:$F$1000,"Sale",Transactions!$A$6:$A$1000,">="&Settings!$B$5,Transactions!$A$6:$A$1000,"<="&Settings!$B$7) -> 459000 | G9: =(INDEX(Register!$D$6:$D$23,MATCH(B9,Register!$A$6:$A$23,0))+INDEX('Reorder Dashboard'!$E$9:$E$26,MATCH(B9,'Reorder Dashboard'!$A$9:$A$26,0)))/2 -> 13.5 | H9: =IF(G9=0,0,D9/G9) -> 4 | I9: =H9*52 -> 208 | J9: =IF(D9=0,"n/a",G9/(D9/Settings!$B$6)) -> 1.5 | K9: =IF(H9>=Settings!$B$13,"Fast-moving",IF(H9<Settings!$B$14,"Slow-moving","Medium")) -> Fast-moving | L9: =RANK(H9,$H$6:$H$23,1)+COUNTIF($H$6:H9,H9)-1 -> 18
A10: =RANK(D10,$D$6:$D$23,0)+COUNTIF($D$6:D10,D10)-1 -> 5 | B10: BEV002 | C10: =INDEX(Register!$B$6:$B$23,MATCH(B10,Register!$A$6:$A$23,0)) -> Orange Soft Drink 50cl PET | D10: =INDEX(Register!$G$6:$G$23,MATCH(B10,Register!$A$6:$A$23,0)) -> 42 | E10: =IFERROR(D10/SUM($D$6:$D$23),0) -> 0.078947368 | F10: =SUMIFS(Transactions!$K$6:$K$1000,Transactions!$C$6:$C$1000,B10,Transactions!$F$6:$F$1000,"Sale",Transactions!$A$6:$A$1000,">="&Settings!$B$5,Transactions!$A$6:$A$1000,"<="&Settings!$B$7) -> 247800 | G10: =(INDEX(Register!$D$6:$D$23,MATCH(B10,Register!$A$6:$A$23,0))+INDEX('Reorder Dashboard'!$E$9:$E$26,MATCH(B10,'Reorder Dashboard'!$A$9:$A$26,0)))/2 -> 28.5 | H10: =IF(G10=0,0,D10/G10) -> 1.4736842 | I10: =H10*52 -> 76.631579 | J10: =IF(D10=0,"n/a",G10/(D10/Settings!$B$6)) -> 4.0714286 | K10: =IF(H10>=Settings!$B$13,"Fast-moving",IF(H10<Settings!$B$14,"Slow-moving","Medium")) -> Fast-moving | L10: =RANK(H10,$H$6:$H$23,1)+COUNTIF($H$6:H10,H10)-1 -> 16
A11: =RANK(D11,$D$6:$D$23,0)+COUNTIF($D$6:D11,D11)-1 -> 6 | B11: FDS004 | C11: =INDEX(Register!$B$6:$B$23,MATCH(B11,Register!$A$6:$A$23,0)) -> Granulated Sugar 500g | D11: =INDEX(Register!$G$6:$G$23,MATCH(B11,Register!$A$6:$A$23,0)) -> 33 | E11: =IFERROR(D11/SUM($D$6:$D$23),0) -> 0.062030075 | F11: =SUMIFS(Transactions!$K$6:$K$1000,Transactions!$C$6:$C$1000,B11,Transactions!$F$6:$F$1000,"Sale",Transactions!$A$6:$A$1000,">="&Settings!$B$5,Transactions!$A$6:$A$1000,"<="&Settings!$B$7) -> 620400 | G11: =(INDEX(Register!$D$6:$D$23,MATCH(B11,Register!$A$6:$A$23,0))+INDEX('Reorder Dashboard'!$E$9:$E$26,MATCH(B11,'Reorder Dashboard'!$A$9:$A$26,0)))/2 -> 84 | H11: =IF(G11=0,0,D11/G11) -> 0.39285714 | I11: =H11*52 -> 20.428571 | J11: =IF(D11=0,"n/a",G11/(D11/Settings!$B$6)) -> 15.272727 | K11: =IF(H11>=Settings!$B$13,"Fast-moving",IF(H11<Settings!$B$14,"Slow-moving","Medium")) -> Slow-moving | L11: =RANK(H11,$H$6:$H$23,1)+COUNTIF($H$6:H11,H11)-1 -> 6
A12: =RANK(D12,$D$6:$D$23,0)+COUNTIF($D$6:D12,D12)-1 -> 7 | B12: DET001 | C12: =INDEX(Register!$B$6:$B$23,MATCH(B12,Register!$A$6:$A$23,0)) -> Detergent Powder 900g | D12: =INDEX(Register!$G$6:$G$23,MATCH(B12,Register!$A$6:$A$23,0)) -> 30 | E12: =IFERROR(D12/SUM($D$6:$D$23),0) -> 0.056390977 | F12: =SUMIFS(Transactions!$K$6:$K$1000,Transactions!$C$6:$C$1000,B12,Transactions!$F$6:$F$1000,"Sale",Transactions!$A$6:$A$1000,">="&Settings!$B$5,Transactions!$A$6:$A$1000,"<="&Settings!$B$7) -> 486000 | G12: =(INDEX(Register!$D$6:$D$23,MATCH(B12,Register!$A$6:$A$23,0))+INDEX('Reorder Dashboard'!$E$9:$E$26,MATCH(B12,'Reorder Dashboard'!$A$9:$A$26,0)))/2 -> 29 | H12: =IF(G12=0,0,D12/G12) -> 1.0344828 | I12: =H12*52 -> 53.793103 | J12: =IF(D12=0,"n/a",G12/(D12/Settings!$B$6)) -> 5.8 | K12: =IF(H12>=Settings!$B$13,"Fast-moving",IF(H12<Settings!$B$14,"Slow-moving","Medium")) -> Fast-moving | L12: =RANK(H12,$H$6:$H$23,1)+COUNTIF($H$6:H12,H12)-1 -> 13
A13: =RANK(D13,$D$6:$D$23,0)+COUNTIF($D$6:D13,D13)-1 -> 8 | B13: FDS002 | C13: =INDEX(Register!$B$6:$B$23,MATCH(B13,Register!$A$6:$A$23,0)) -> Tomato Paste 70g Sachet | D13: =INDEX(Register!$G$6:$G$23,MATCH(B13,Register!$A$6:$A$23,0)) -> 26 | E13: =IFERROR(D13/SUM($D$6:$D$23),0) -> 0.04887218 | F13: =SUMIFS(Transactions!$K$6:$K$1000,Transactions!$C$6:$C$1000,B13,Transactions!$F$6:$F$1000,"Sale",Transactions!$A$6:$A$1000,">="&Settings!$B$5,Transactions!$A$6:$A$1000,"<="&Settings!$B$7) -> 447200 | G13: =(INDEX(Register!$D$6:$D$23,MATCH(B13,Register!$A$6:$A$23,0))+INDEX('Reorder Dashboard'!$E$9:$E$26,MATCH(B13,'Reorder Dashboard'!$A$9:$A$26,0)))/2 -> 39.5 | H13: =IF(G13=0,0,D13/G13) -> 0.65822785 | I13: =H13*52 -> 34.227848 | J13: =IF(D13=0,"n/a",G13/(D13/Settings!$B$6)) -> 9.1153846 | K13: =IF(H13>=Settings!$B$13,"Fast-moving",IF(H13<Settings!$B$14,"Slow-moving","Medium")) -> Medium | L13: =RANK(H13,$H$6:$H$23,1)+COUNTIF($H$6:H13,H13)-1 -> 10
A14: =RANK(D14,$D$6:$D$23,0)+COUNTIF($D$6:D14,D14)-1 -> 9 | B14: OIL001 | C14: =INDEX(Register!$B$6:$B$23,MATCH(B14,Register!$A$6:$A$23,0)) -> Vegetable Oil 5L | D14: =INDEX(Register!$G$6:$G$23,MATCH(B14,Register!$A$6:$A$23,0)) -> 24 | E14: =IFERROR(D14/SUM($D$6:$D$23),0) -> 0.045112782 | F14: =SUMIFS(Transactions!$K$6:$K$1000,Transactions!$C$6:$C$1000,B14,Transactions!$F$6:$F$1000,"Sale",Transactions!$A$6:$A$1000,">="&Settings!$B$5,Transactions!$A$6:$A$1000,"<="&Settings!$B$7) -> 996000 | G14: =(INDEX(Register!$D$6:$D$23,MATCH(B14,Register!$A$6:$A$23,0))+INDEX('Reorder Dashboard'!$E$9:$E$26,MATCH(B14,'Reorder Dashboard'!$A$9:$A$26,0)))/2 -> 22 | H14: =IF(G14=0,0,D14/G14) -> 1.0909091 | I14: =H14*52 -> 56.727273 | J14: =IF(D14=0,"n/a",G14/(D14/Settings!$B$6)) -> 5.5 | K14: =IF(H14>=Settings!$B$13,"Fast-moving",IF(H14<Settings!$B$14,"Slow-moving","Medium")) -> Fast-moving | L14: =RANK(H14,$H$6:$H$23,1)+COUNTIF($H$6:H14,H14)-1 -> 14
A15: =RANK(D15,$D$6:$D$23,0)+COUNTIF($D$6:D15,D15)-1 -> 10 | B15: DET002 | C15: =INDEX(Register!$B$6:$B$23,MATCH(B15,Register!$A$6:$A$23,0)) -> Detergent Powder 400g | D15: =INDEX(Register!$G$6:$G$23,MATCH(B15,Register!$A$6:$A$23,0)) -> 20 | E15: =IFERROR(D15/SUM($D$6:$D$23),0) -> 0.037593985 | F15: =SUMIFS(Transactions!$K$6:$K$1000,Transactions!$C$6:$C$1000,B15,Transactions!$F$6:$F$1000,"Sale",Transactions!$A$6:$A$1000,">="&Settings!$B$5,Transactions!$A$6:$A$1000,"<="&Settings!$B$7) -> 380000 | G15: =(INDEX(Register!$D$6:$D$23,MATCH(B15,Register!$A$6:$A$23,0))+INDEX('Reorder Dashboard'!$E$9:$E$26,MATCH(B15,'Reorder Dashboard'!$A$9:$A$26,0)))/2 -> 40.5 | H15: =IF(G15=0,0,D15/G15) -> 0.49382716 | I15: =H15*52 -> 25.679012 | J15: =IF(D15=0,"n/a",G15/(D15/Settings!$B$6)) -> 12.15 | K15: =IF(H15>=Settings!$B$13,"Fast-moving",IF(H15<Settings!$B$14,"Slow-moving","Medium")) -> Slow-moving | L15: =RANK(H15,$H$6:$H$23,1)+COUNTIF($H$6:H15,H15)-1 -> 9
A16: =RANK(D16,$D$6:$D$23,0)+COUNTIF($D$6:D16,D16)-1 -> 11 | B16: FDS001 | C16: =INDEX(Register!$B$6:$B$23,MATCH(B16,Register!$A$6:$A$23,0)) -> Evaporated Milk 160g Tin | D16: =INDEX(Register!$G$6:$G$23,MATCH(B16,Register!$A$6:$A$23,0)) -> 18 | E16: =IFERROR(D16/SUM($D$6:$D$23),0) -> 0.033834586 | F16: =SUMIFS(Transactions!$K$6:$K$1000,Transactions!$C$6:$C$1000,B16,Transactions!$F$6:$F$1000,"Sale",Transactions!$A$6:$A$1000,">="&Settings!$B$5,Transactions!$A$6:$A$1000,"<="&Settings!$B$7) -> 558000 | G16: =(INDEX(Register!$D$6:$D$23,MATCH(B16,Register!$A$6:$A$23,0))+INDEX('Reorder Dashboard'!$E$9:$E$26,MATCH(B16,'Reorder Dashboard'!$A$9:$A$26,0)))/2 -> 19 | H16: =IF(G16=0,0,D16/G16) -> 0.94736842 | I16: =H16*52 -> 49.263158 | J16: =IF(D16=0,"n/a",G16/(D16/Settings!$B$6)) -> 6.3333333 | K16: =IF(H16>=Settings!$B$13,"Fast-moving",IF(H16<Settings!$B$14,"Slow-moving","Medium")) -> Medium | L16: =RANK(H16,$H$6:$H$23,1)+COUNTIF($H$6:H16,H16)-1 -> 12
A17: =RANK(D17,$D$6:$D$23,0)+COUNTIF($D$6:D17,D17)-1 -> 12 | B17: FDS003 | C17: =INDEX(Register!$B$6:$B$23,MATCH(B17,Register!$A$6:$A$23,0)) -> Seasoning Cubes | D17: =INDEX(Register!$G$6:$G$23,MATCH(B17,Register!$A$6:$A$23,0)) -> 15 | E17: =IFERROR(D17/SUM($D$6:$D$23),0) -> 0.028195489 | F17: =SUMIFS(Transactions!$K$6:$K$1000,Transactions!$C$6:$C$1000,B17,Transactions!$F$6:$F$1000,"Sale",Transactions!$A$6:$A$1000,">="&Settings!$B$5,Transactions!$A$6:$A$1000,"<="&Settings!$B$7) -> 232500 | G17: =(INDEX(Register!$D$6:$D$23,MATCH(B17,Register!$A$6:$A$23,0))+INDEX('Reorder Dashboard'!$E$9:$E$26,MATCH(B17,'Reorder Dashboard'!$A$9:$A$26,0)))/2 -> 42.5 | H17: =IF(G17=0,0,D17/G17) -> 0.35294118 | I17: =H17*52 -> 18.352941 | J17: =IF(D17=0,"n/a",G17/(D17/Settings!$B$6)) -> 17 | K17: =IF(H17>=Settings!$B$13,"Fast-moving",IF(H17<Settings!$B$14,"Slow-moving","Medium")) -> Slow-moving | L17: =RANK(H17,$H$6:$H$23,1)+COUNTIF($H$6:H17,H17)-1 -> 5
... A23: =RANK(D23,$D$6:$D$23,0)+COUNTIF($D$6:D23,D23)-1 -> 18 | B23: FDS005 | C23: =INDEX(Register!$B$6:$B$23,MATCH(B23,Register!$A$6:$A$23,0)) -> Table Salt 500g | D23: =INDEX(Register!$G$6:$G$23,MATCH(B23,Register!$A$6:$A$23,0)) -> 4 | E23: =IFERROR(D23/SUM($D$6:$D$23),0) -> 0.007518797 | F23: =SUMIFS(Transactions!$K$6:$K$1000,Transactions!$C$6:$C$1000,B23,Transactions!$F$6:$F$1000,"Sale",Transactions!$A$6:$A$1000,">="&Settings!$B$5,Transactions!$A$6:$A$1000,"<="&Settings!$B$7) -> 29600 | G23: =(INDEX(Register!$D$6:$D$23,MATCH(B23,Register!$A$6:$A$23,0))+INDEX('Reorder Dashboard'!$E$9:$E$26,MATCH(B23,'Reorder Dashboard'!$A$9:$A$26,0)))/2 -> 22 | H23: =IF(G23=0,0,D23/G23) -> 0.18181818 | I23: =H23*52 -> 9.4545455 | J23: =IF(D23=0,"n/a",G23/(D23/Settings!$B$6)) -> 33 | K23: =IF(H23>=Settings!$B$13,"Fast-moving",IF(H23<Settings!$B$14,"Slow-moving","Medium")) -> Slow-moving | L23: =RANK(H23,$H$6:$H$23,1)+COUNTIF($H$6:H23,H23)-1 -> 1
A24: TOTAL | D24: =SUM(D6:D23) -> 532 | F24: =SUM(F6:F23) -> 6588900
A26: Classification count
A27: Fast-moving | C27: =COUNTIF($K$6:$K$23,A27) -> 6
A28: Medium | C28: =COUNTIF($K$6:$K$23,A28) -> 3
A29: Slow-moving | C29: =COUNTIF($K$6:$K$23,A29) -> 9

Sheet Sales Summary
A1: Sales Summary (pivot-style SUMIFS tables)
A2: Sales are valued at list price. Sales Returns are shown separately and deducted to give net sales.
A5: Date | B5: Day | C5: Sale Lines | D5: Cartons Sold | E5: Cash Sales (₦) | F5: Transfer Sales (₦) | G5: Credit Sales (₦) | H5: Gross Sales (₦) | I5: Sales Returns (₦) | J5: Net Sales (₦)
A6: =Settings!$B$5+0 -> 46314 | B6: =TEXT(A6,"ddd") -> Mon | C6: =COUNTIFS(Transactions!$A$6:$A$1000,A6,Transactions!$F$6:$F$1000,"Sale") -> 33 | D6: =SUMIFS(Transactions!$G$6:$G$1000,Transactions!$A$6:$A$1000,A6,Transactions!$F$6:$F$1000,"Sale") -> 75 | E6: =SUMIFS(Transactions!$K$6:$K$1000,Transactions!$A$6:$A$1000,$A6,Transactions!$F$6:$F$1000,"Sale",Transactions!$I$6:$I$1000,"Cash") -> 258200 | F6: =SUMIFS(Transactions!$K$6:$K$1000,Transactions!$A$6:$A$1000,$A6,Transactions!$F$6:$F$1000,"Sale",Transactions!$I$6:$I$1000,"Transfer") -> 326100 | G6: =SUMIFS(Transactions!$K$6:$K$1000,Transactions!$A$6:$A$1000,$A6,Transactions!$F$6:$F$1000,"Sale",Transactions!$I$6:$I$1000,"Credit") -> 322600 | H6: =SUMIFS(Transactions!$K$6:$K$1000,Transactions!$A$6:$A$1000,A6,Transactions!$F$6:$F$1000,"Sale") -> 906900 | I6: =SUMIFS(Transactions!$K$6:$K$1000,Transactions!$A$6:$A$1000,A6,Transactions!$F$6:$F$1000,"Sales Return") -> 0 | J6: =H6-I6 -> 906900
A7: =Settings!$B$5+1 -> 46315 | B7: =TEXT(A7,"ddd") -> Tue | C7: =COUNTIFS(Transactions!$A$6:$A$1000,A7,Transactions!$F$6:$F$1000,"Sale") -> 27 | D7: =SUMIFS(Transactions!$G$6:$G$1000,Transactions!$A$6:$A$1000,A7,Transactions!$F$6:$F$1000,"Sale") -> 72 | E7: =SUMIFS(Transactions!$K$6:$K$1000,Transactions!$A$6:$A$1000,$A7,Transactions!$F$6:$F$1000,"Sale",Transactions!$I$6:$I$1000,"Cash") -> 428500 | F7: =SUMIFS(Transactions!$K$6:$K$1000,Transactions!$A$6:$A$1000,$A7,Transactions!$F$6:$F$1000,"Sale",Transactions!$I$6:$I$1000,"Transfer") -> 102900 | G7: =SUMIFS(Transactions!$K$6:$K$1000,Transactions!$A$6:$A$1000,$A7,Transactions!$F$6:$F$1000,"Sale",Transactions!$I$6:$I$1000,"Credit") -> 306300 | H7: =SUMIFS(Transactions!$K$6:$K$1000,Transactions!$A$6:$A$1000,A7,Transactions!$F$6:$F$1000,"Sale") -> 837700 | I7: =SUMIFS(Transactions!$K$6:$K$1000,Transactions!$A$6:$A$1000,A7,Transactions!$F$6:$F$1000,"Sales Return") -> 16200 | J7: =H7-I7 -> 821500
A8: =Settings!$B$5+2 -> 46316 | B8: =TEXT(A8,"ddd") -> Wed | C8: =COUNTIFS(Transactions!$A$6:$A$1000,A8,Transactions!$F$6:$F$1000,"Sale") -> 17 | D8: =SUMIFS(Transactions!$G$6:$G$1000,Transactions!$A$6:$A$1000,A8,Transactions!$F$6:$F$1000,"Sale") -> 63 | E8: =SUMIFS(Transactions!$K$6:$K$1000,Transactions!$A$6:$A$1000,$A8,Transactions!$F$6:$F$1000,"Sale",Transactions!$I$6:$I$1000,"Cash") -> 99600 | F8: =SUMIFS(Transactions!$K$6:$K$1000,Transactions!$A$6:$A$1000,$A8,Transactions!$F$6:$F$1000,"Sale",Transactions!$I$6:$I$1000,"Transfer") -> 185800 | G8: =SUMIFS(Transactions!$K$6:$K$1000,Transactions!$A$6:$A$1000,$A8,Transactions!$F$6:$F$1000,"Sale",Transactions!$I$6:$I$1000,"Credit") -> 454600 | H8: =SUMIFS(Transactions!$K$6:$K$1000,Transactions!$A$6:$A$1000,A8,Transactions!$F$6:$F$1000,"Sale") -> 740000 | I8: =SUMIFS(Transactions!$K$6:$K$1000,Transactions!$A$6:$A$1000,A8,Transactions!$F$6:$F$1000,"Sales Return") -> 34000 | J8: =H8-I8 -> 706000
A9: =Settings!$B$5+3 -> 46317 | B9: =TEXT(A9,"ddd") -> Thu | C9: =COUNTIFS(Transactions!$A$6:$A$1000,A9,Transactions!$F$6:$F$1000,"Sale") -> 29 | D9: =SUMIFS(Transactions!$G$6:$G$1000,Transactions!$A$6:$A$1000,A9,Transactions!$F$6:$F$1000,"Sale") -> 94 | E9: =SUMIFS(Transactions!$K$6:$K$1000,Transactions!$A$6:$A$1000,$A9,Transactions!$F$6:$F$1000,"Sale",Transactions!$I$6:$I$1000,"Cash") -> 364400 | F9: =SUMIFS(Transactions!$K$6:$K$1000,Transactions!$A$6:$A$1000,$A9,Transactions!$F$6:$F$1000,"Sale",Transactions!$I$6:$I$1000,"Transfer") -> 296400 | G9: =SUMIFS(Transactions!$K$6:$K$1000,Transactions!$A$6:$A$1000,$A9,Transactions!$F$6:$F$1000,"Sale",Transactions!$I$6:$I$1000,"Credit") -> 429700 | H9: =SUMIFS(Transactions!$K$6:$K$1000,Transactions!$A$6:$A$1000,A9,Transactions!$F$6:$F$1000,"Sale") -> 1090500 | I9: =SUMIFS(Transactions!$K$6:$K$1000,Transactions!$A$6:$A$1000,A9,Transactions!$F$6:$F$1000,"Sales Return") -> 72500 | J9: =H9-I9 -> 1018000
A10: =Settings!$B$5+4 -> 46318 | B10: =TEXT(A10,"ddd") -> Fri | C10: =COUNTIFS(Transactions!$A$6:$A$1000,A10,Transactions!$F$6:$F$1000,"Sale") -> 33 | D10: =SUMIFS(Transactions!$G$6:$G$1000,Transactions!$A$6:$A$1000,A10,Transactions!$F$6:$F$1000,"Sale") -> 95 | E10: =SUMIFS(Transactions!$K$6:$K$1000,Transactions!$A$6:$A$1000,$A10,Transactions!$F$6:$F$1000,"Sale",Transactions!$I$6:$I$1000,"Cash") -> 490200 | F10: =SUMIFS(Transactions!$K$6:$K$1000,Transactions!$A$6:$A$1000,$A10,Transactions!$F$6:$F$1000,"Sale",Transactions!$I$6:$I$1000,"Transfer") -> 167800 | G10: =SUMIFS(Transactions!$K$6:$K$1000,Transactions!$A$6:$A$1000,$A10,Transactions!$F$6:$F$1000,"Sale",Transactions!$I$6:$I$1000,"Credit") -> 471700 | H10: =SUMIFS(Transactions!$K$6:$K$1000,Transactions!$A$6:$A$1000,A10,Transactions!$F$6:$F$1000,"Sale") -> 1129700 | I10: =SUMIFS(Transactions!$K$6:$K$1000,Transactions!$A$6:$A$1000,A10,Transactions!$F$6:$F$1000,"Sales Return") -> 11800 | J10: =H10-I10 -> 1117900
A11: =Settings!$B$5+5 -> 46319 | B11: =TEXT(A11,"ddd") -> Sat | C11: =COUNTIFS(Transactions!$A$6:$A$1000,A11,Transactions!$F$6:$F$1000,"Sale") -> 35 | D11: =SUMIFS(Transactions!$G$6:$G$1000,Transactions!$A$6:$A$1000,A11,Transactions!$F$6:$F$1000,"Sale") -> 133 | E11: =SUMIFS(Transactions!$K$6:$K$1000,Transactions!$A$6:$A$1000,$A11,Transactions!$F$6:$F$1000,"Sale",Transactions!$I$6:$I$1000,"Cash") -> 436900 | F11: =SUMIFS(Transactions!$K$6:$K$1000,Transactions!$A$6:$A$1000,$A11,Transactions!$F$6:$F$1000,"Sale",Transactions!$I$6:$I$1000,"Transfer") -> 893900 | G11: =SUMIFS(Transactions!$K$6:$K$1000,Transactions!$A$6:$A$1000,$A11,Transactions!$F$6:$F$1000,"Sale",Transactions!$I$6:$I$1000,"Credit") -> 553300 | H11: =SUMIFS(Transactions!$K$6:$K$1000,Transactions!$A$6:$A$1000,A11,Transactions!$F$6:$F$1000,"Sale") -> 1884100 | I11: =SUMIFS(Transactions!$K$6:$K$1000,Transactions!$A$6:$A$1000,A11,Transactions!$F$6:$F$1000,"Sales Return") -> 4600 | J11: =H11-I11 -> 1879500
A12: TOTAL | C12: =SUM(C6:C11) -> 174 | D12: =SUM(D6:D11) -> 532 | E12: =SUM(E6:E11) -> 2077800 | F12: =SUM(F6:F11) -> 1972900 | G12: =SUM(G6:G11) -> 2538200 | H12: =SUM(H6:H11) -> 6588900 | I12: =SUM(I6:I11) -> 139100 | J12: =SUM(J6:J11) -> 6449800
A13: Check: cash + transfer + credit equals gross sales (difference should be 0, otherwise a Sale line is missing its Terms) | J13: =H12-E12-F12-G12 -> 0
A15: Sales by category
A16: Category | C16: Units Sold | D16: Sales Value (₦) | E16: Share of Sales
A17: Beverages | C17: =SUMIFS(Transactions!$G$6:$G$1000,Transactions!$E$6:$E$1000,$A17,Transactions!$F$6:$F$1000,"Sale",Transactions!$A$6:$A$1000,">="&Settings!$B$5,Transactions!$A$6:$A$1000,"<="&Settings!$B$7) -> 183 | D17: =SUMIFS(Transactions!$K$6:$K$1000,Transactions!$E$6:$E$1000,$A17,Transactions!$F$6:$F$1000,"Sale",Transactions!$A$6:$A$1000,">="&Settings!$B$5,Transactions!$A$6:$A$1000,"<="&Settings!$B$7) -> 868200 | E17: =IFERROR(D17/$D$22,0) -> 0.13176706
A18: Noodles & Pasta | C18: =SUMIFS(Transactions!$G$6:$G$1000,Transactions!$E$6:$E$1000,$A18,Transactions!$F$6:$F$1000,"Sale",Transactions!$A$6:$A$1000,">="&Settings!$B$5,Transactions!$A$6:$A$1000,"<="&Settings!$B$7) -> 156 | D18: =SUMIFS(Transactions!$K$6:$K$1000,Transactions!$E$6:$E$1000,$A18,Transactions!$F$6:$F$1000,"Sale",Transactions!$A$6:$A$1000,">="&Settings!$B$5,Transactions!$A$6:$A$1000,"<="&Settings!$B$7) -> 1368600 | E18: =IFERROR(D18/$D$22,0) -> 0.20771297
A19: Cooking Oil | C19: =SUMIFS(Transactions!$G$6:$G$1000,Transactions!$E$6:$E$1000,$A19,Transactions!$F$6:$F$1000,"Sale",Transactions!$A$6:$A$1000,">="&Settings!$B$5,Transactions!$A$6:$A$1000,"<="&Settings!$B$7) -> 34 | D19: =SUMIFS(Transactions!$K$6:$K$1000,Transactions!$E$6:$E$1000,$A19,Transactions!$F$6:$F$1000,"Sale",Transactions!$A$6:$A$1000,">="&Settings!$B$5,Transactions!$A$6:$A$1000,"<="&Settings!$B$7) -> 1386000 | E19: =IFERROR(D19/$D$22,0) -> 0.21035378
A20: Home Care | C20: =SUMIFS(Transactions!$G$6:$G$1000,Transactions!$E$6:$E$1000,$A20,Transactions!$F$6:$F$1000,"Sale",Transactions!$A$6:$A$1000,">="&Settings!$B$5,Transactions!$A$6:$A$1000,"<="&Settings!$B$7) -> 57 | D20: =SUMIFS(Transactions!$K$6:$K$1000,Transactions!$E$6:$E$1000,$A20,Transactions!$F$6:$F$1000,"Sale",Transactions!$A$6:$A$1000,">="&Settings!$B$5,Transactions!$A$6:$A$1000,"<="&Settings!$B$7) -> 937400 | E20: =IFERROR(D20/$D$22,0) -> 0.14226957
A21: Packaged Food | C21: =SUMIFS(Transactions!$G$6:$G$1000,Transactions!$E$6:$E$1000,$A21,Transactions!$F$6:$F$1000,"Sale",Transactions!$A$6:$A$1000,">="&Settings!$B$5,Transactions!$A$6:$A$1000,"<="&Settings!$B$7) -> 102 | D21: =SUMIFS(Transactions!$K$6:$K$1000,Transactions!$E$6:$E$1000,$A21,Transactions!$F$6:$F$1000,"Sale",Transactions!$A$6:$A$1000,">="&Settings!$B$5,Transactions!$A$6:$A$1000,"<="&Settings!$B$7) -> 2028700 | E21: =IFERROR(D21/$D$22,0) -> 0.30789661
A22: TOTAL | C22: =SUM(C17:C21) -> 532 | D22: =SUM(D17:D21) -> 6588900 | E22: =SUM(E17:E21) -> 1
